Workbook
Name products: products!$1:$1000
Name product_id: events!$N$2:$N$1331
Name total_revenue: events!$U$2:$U$1331
Name countries: countries!$1:$1000
Name total_profit: events!$W$2:$W$1331
Name total_cost: events!$V$2:$V$1331

Sheet countries
A1: alpha-3 | B1: name | C1: alpha-2 | D1: alpha-3 | E1: region | F1: sub-region
A2: AFG | B2: Afghanistan | C2: AF | D2: AFG | E2: Asia | F2: Southern Asia
A3: ALA | B3: Åland Islands | C3: AX | D3: ALA | E3: Europe | F3: Northern Europe
A4: ALB | B4: Albania | C4: AL | D4: ALB | E4: Europe | F4: Southern Europe
A5: DZA | B5: Algeria | C5: DZ | D5: DZA | E5: Africa | F5: Northern Africa
A6: ASM | B6: American Samoa | C6: AS | D6: ASM | E6: Oceania | F6: Polynesia
A7: AND | B7: Andorra | C7: AD | D7: AND | E7: Europe | F7: Southern Europe
A8: AGO | B8: Angola | C8: AO | D8: AGO | E8: Africa | F8: Sub-Saharan Africa
A9: AIA | B9: Anguilla | C9: AI | D9: AIA | E9: Americas | F9: Latin America and the Caribbean
A10: ATA | B10: Antarctica | C10: AQ | D10: ATA | E10: Antarctic | F10: Antarctic
A11: ATG | B11: Antigua and Barbuda | C11: AG | D11: ATG | E11: Americas | F11: Latin America and the Caribbean
A12: ARG | B12: Argentina | C12: AR | D12: ARG | E12: Americas | F12: Latin America and the Caribbean
... A250: ZWE | B250: Zimbabwe | C250: ZW | D250: ZWE | E250: Africa | F250: Sub-Saharan Africa

Sheet events
A1: Order ID | B1: Order Date | C1: Year of order | D1: Month of order | E1: Weekday | F1: Number of weekday | G1: Ship Date | H1: Shipping Duration | I1: Order Priority | J1: Country Code | K1: Countries | L1: region | M1: sub-region | N1: Product ID | O1: Category | P1: Sales Channel | Q1: Units Sold | R1: Unit Price | S1: Unit Cost | U1: total revenue | V1: total cost | W1: total profit
A2: 100640618 | B2: 41920 | C2: =YEAR(B2) -> 2014 | D2: =TEXT(B2,"MM - MMM") -> 10 - Oct | E2: =CHOOSE(WEEKDAY(B2,2),"Mon","Tue","Wed","Thu","Fri","Sat","Sun") -> Wed | F2: =MATCH(E2,{"Mon","Tue","Wed","Thu","Fri","Sat","Sun"}, 0) -> 3 | G2: 41930 | H2: =(DATEDIF(B2,G2,"D")) -> 10 | I2: M | J2: NOR | K2: =VLOOKUP(J2,countries,2,false) -> Norway | L2: =VLOOKUP($J2,countries,5,false) -> Europe | M2: =VLOOKUP($J2,countries,6,false) -> Northern Europe | N2: 2103 | O2: =VLOOKUP(N2, products, 2, FALSE) -> Cereal | P2: Online | Q2: 650 | R2: 205.7 | S2: 117.11 | U2: =Q2*R2 -> 133705 | V2: =Q2*S2 -> 76121.5 | W2: =U2-V2 -> 57583.5
A3: 100983083 | B3: 42593 | C3: =YEAR(B3) -> 2016 | D3: =TEXT(B3,"MM - MMM") -> 08 - Aug | E3: =CHOOSE(WEEKDAY(B3,2),"Mon","Tue","Wed","Thu","Fri","Sat","Sun") -> Thu | F3: =MATCH(E3,{"Mon","Tue","Wed","Thu","Fri","Sat","Sun"}, 0) -> 4 | G3: 42593 | H3: =(DATEDIF(B3,G3,"D")) -> 0 | I3: C | J3: SRB | K3: =VLOOKUP(J3,countries,2,false) -> Serbia | L3: =VLOOKUP($J3,countries,5,false) -> Europe | M3: =VLOOKUP($J3,countries,6,false) -> Southern Europe | N3: 2103 | O3: =VLOOKUP(N3, products, 2, FALSE) -> Cereal | P3: Offline | Q3: 1993 | R3: 205.7 | S3: 117.11 | U3: =Q3*R3 -> 409960.1 | V3: =Q3*S3 -> 233400.23 | W3: =U3-V3 -> 176559.87
A4: 101025998 | B4: 41838 | C4: =YEAR(B4) -> 2014 | D4: =TEXT(B4,"MM - MMM") -> 07 - Jul | E4: =CHOOSE(WEEKDAY(B4,2),"Mon","Tue","Wed","Thu","Fri","Sat","Sun") -> Fri | F4: =MATCH(E4,{"Mon","Tue","Wed","Thu","Fri","Sat","Sun"}, 0) -> 5 | G4: 41862 | H4: =(DATEDIF(B4,G4,"D")) -> 24 | I4: M | J4: Unknown | K4: Unknown | L4: Unknown | M4: Unknown | N4: 7940 | O4: =VLOOKUP(N4, products, 2, FALSE) -> Household | P4: Online | Q4: 4693 | R4: 668.27 | S4: 502.54 | U4: =Q4*R4 -> 3136191.1 | V4: =Q4*S4 -> 2358420.2 | W4: =U4-V4 -> 777770.89
A5: 102230632 | B5: 42868 | C5: =YEAR(B5) -> 2017 | D5: =TEXT(B5,"MM - MMM") -> 05 - May | E5: =CHOOSE(WEEKDAY(B5,2),"Mon","Tue","Wed","Thu","Fri","Sat","Sun") -> Sat | F5: =MATCH(E5,{"Mon","Tue","Wed","Thu","Fri","Sat","Sun"}, 0) -> 6 | G5: 42899 | H5: =(DATEDIF(B5,G5,"D")) -> 31 | I5: L | J5: MNE | K5: =VLOOKUP(J5,countries,2,false) -> Montenegro | L5: =VLOOKUP($J5,countries,5,false) -> Europe | M5: =VLOOKUP($J5,countries,6,false) -> Southern Europe | N5: 2455 | O5: =VLOOKUP(N5, products, 2, FALSE) -> Clothes | P5: Online | Q5: 1171 | R5: 109.28 | S5: 35.84 | U5: =Q5*R5 -> 127966.88 | V5: =Q5*S5 -> 41968.64 | W5: =U5-V5 -> 85998.24
A6: 103435266 | B6: 41132 | C6: =YEAR(B6) -> 2012 | D6: =TEXT(B6,"MM - MMM") -> 08 - Aug | E6: =CHOOSE(WEEKDAY(B6,2),"Mon","Tue","Wed","Thu","Fri","Sat","Sun") -> Sat | F6: =MATCH(E6,{"Mon","Tue","Wed","Thu","Fri","Sat","Sun"}, 0) -> 6 | G6: 41170 | H6: =(DATEDIF(B6,G6,"D")) -> 38 | I6: H | J6: SRB | K6: =VLOOKUP(J6,countries,2,false) -> Serbia | L6: =VLOOKUP($J6,countries,5,false) -> Europe | M6: =VLOOKUP($J6,countries,6,false) -> Southern Europe | N6: 1270 | O6: =VLOOKUP(N6, products, 2, FALSE) -> Beverages | P6: Offline | Q6: 7648 | R6: 47.45 | S6: 31.79 | U6: =Q6*R6 -> 362897.6 | V6: =Q6*S6 -> 243129.92 | W6: =U6-V6 -> 119767.68
A7: 103450715 | B7: 42078 | C7: =YEAR(B7) -> 2015 | D7: =TEXT(B7,"MM - MMM") -> 03 - Mar | E7: =CHOOSE(WEEKDAY(B7,2),"Mon","Tue","Wed","Thu","Fri","Sat","Sun") -> Sun | F7: =MATCH(E7,{"Mon","Tue","Wed","Thu","Fri","Sat","Sun"}, 0) -> 7 | G7: 42112 | H7: =(DATEDIF(B7,G7,"D")) -> 34 | I7: H | J7: SVK | K7: =VLOOKUP(J7,countries,2,false) -> Slovakia | L7: =VLOOKUP($J7,countries,5,false) -> Europe | M7: =VLOOKUP($J7,countries,6,false) -> Eastern Europe | N7: 8681 | O7: =VLOOKUP(N7, products, 2, FALSE) -> Office Supplies | P7: Online | Q7: 2220 | R7: 651.21 | S7: 524.96 | U7: =Q7*R7 -> 1445686.2 | V7: =Q7*S7 -> 1165411.2 | W7: =U7-V7 -> 280275
A8: 103499639 | B8: 41384 | C8: =YEAR(B8) -> 2013 | D8: =TEXT(B8,"MM - MMM") -> 04 - Apr | E8: =CHOOSE(WEEKDAY(B8,2),"Mon","Tue","Wed","Thu","Fri","Sat","Sun") -> Sat | F8: =MATCH(E8,{"Mon","Tue","Wed","Thu","Fri","Sat","Sun"}, 0) -> 6 | G8: 41431 | H8: =(DATEDIF(B8,G8,"D")) -> 47 | I8: L | J8: FRA | K8: =VLOOKUP(J8,countries,2,false) -> France | L8: =VLOOKUP($J8,countries,5,false) -> Europe | M8: =VLOOKUP($J8,countries,6,false) -> Western Europe | N8: 4594 | O8: =VLOOKUP(N8, products, 2, FALSE) -> Fruits | P8: Online | Q8: 6698 | R8: 9.33 | S8: 6.92 | U8: =Q8*R8 -> 62492.34 | V8: =Q8*S8 -> 46350.16 | W8: =U8-V8 -> 16142.18
A9: 103762280 | B9: 40859 | C9: =YEAR(B9) -> 2011 | D9: =TEXT(B9,"MM - MMM") -> 11 - Nov | E9: =CHOOSE(WEEKDAY(B9,2),"Mon","Tue","Wed","Thu","Fri","Sat","Sun") -> Sat | F9: =MATCH(E9,{"Mon","Tue","Wed","Thu","Fri","Sat","Sun"}, 0) -> 6 | G9: 40891 | H9: =(DATEDIF(B9,G9,"D")) -> 32 | I9: M | J9: ESP | K9: =VLOOKUP(J9,countries,2,false) -> Spain | L9: =VLOOKUP($J9,countries,5,false) -> Europe | M9: =VLOOKUP($J9,countries,6,false) -> Southern Europe | N9: 5988 | O9: =VLOOKUP(N9, products, 2, FALSE) -> Vegetables | P9: Online | Q9: 4419 | R9: 154.06 | S9: 90.93 | U9: =Q9*R9 -> 680791.14 | V9: =Q9*S9 -> 401819.67 | W9: =U9-V9 -> 278971.47
A10: 103832662 | B10: 41171 | C10: =YEAR(B10) -> 2012 | D10: =TEXT(B10,"MM - MMM") -> 09 - Sep | E10: =CHOOSE(WEEKDAY(B10,2),"Mon","Tue","Wed","Thu","Fri","Sat","Sun") -> Wed | F10: =MATCH(E10,{"Mon","Tue","Wed","Thu","Fri","Sat","Sun"}, 0) -> 3 | G10: 41202 | H10: =(DATEDIF(B10,G10,"D")) -> 31 | I10: H | J10: HRV | K10: =VLOOKUP(J10,countries,2,false) -> Croatia | L10: =VLOOKUP($J10,countries,5,false) -> Europe | M10: =VLOOKUP($J10,countries,6,false) -> Southern Europe | N10: 7331 | O10: =VLOOKUP(N10, products, 2, FALSE) -> Baby Food | P10: Offline | Q10: 5247 | R10: 255.28 | S10: 159.42 | U10: =Q10*R10 -> 1339454.2 | V10: =Q10*S10 -> 836476.74 | W10: =U10-V10 -> 502977.42
A11: 104008615 | B11: 40566 | C11: =YEAR(B11) -> 2011 | D11: =TEXT(B11,"MM - MMM") -> 01 - Jan | E11: =CHOOSE(WEEKDAY(B11,2),"Mon","Tue","Wed","Thu","Fri","Sat","Sun") -> Sun | F11: =MATCH(E11,{"Mon","Tue","Wed","Thu","Fri","Sat","Sun"}, 0) -> 7 | G11: 40596 | H11: =(DATEDIF(B11,G11,"D")) -> 30 | I11: M | J11: DEU | K11: =VLOOKUP(J11,countries,2,false) -> Germany | L11: =VLOOKUP($J11,countries,5,false) -> Europe | M11: =VLOOKUP($J11,countries,6,false) -> Western Europe | N11: 2103 | O11: =VLOOKUP(N11, products, 2, FALSE) -> Cereal | P11: Online | Q11: 7315 | R11: 205.7 | S11: 117.11 | U11: =Q11*R11 -> 1504695.5 | V11: =Q11*S11 -> 856659.65 | W11: =U11-V11 -> 648035.85
A12: 104165685 | B12: 40958 | C12: =YEAR(B12) -> 2012 | D12: =TEXT(B12,"MM - MMM") -> 02 - Feb | E12: =CHOOSE(WEEKDAY(B12,2),"Mon","Tue","Wed","Thu","Fri","Sat","Sun") -> Sun | F12: =MATCH(E12,{"Mon","Tue","Wed","Thu","Fri","Sat","Sun"}, 0) -> 7 | G12: 40974 | H12: =(DATEDIF(B12,G12,"D")) -> 16 | I12: L | J12: ARM | K12: =VLOOKUP(J12,countries,2,false) -> Armenia | L12: =VLOOKUP($J12,countries,5,false) -> Asia | M12: =VLOOKUP($J12,countries,6,false) -> Western Asia | N12: 7940 | O12: =VLOOKUP(N12, products, 2, FALSE) -> Household | P12: Online | Q12: 3796 | R12: 668.27 | S12: 502.54 | U12: =Q12*R12 -> 2536752.9 | V12: =Q12*S12 -> 1907641.8 | W12: =U12-V12 -> 629111.08
A13: 104190576 | B13: 42788 | C13: =YEAR(B13) -> 2017 | D13: =TEXT(B13,"MM - MMM") -> 02 - Feb | E13: =CHOOSE(WEEKDAY(B13,2),"Mon","Tue","Wed","Thu","Fri","Sat","Sun") -> Wed | F13: =MATCH(E13,{"Mon","Tue","Wed","Thu","Fri","Sat","Sun"}, 0) -> 3 | G13: 42806 | H13: =(DATEDIF(B13,G13,"D")) -> 18 | I13: C | J13: GEO | K13: =VLOOKUP(J13,countries,2,false) -> Georgia | L13: =VLOOKUP($J13,countries,5,false) -> Asia | M13: =VLOOKUP($J13,countries,6,false) -> Western Asia | N13: 8875 | O13: =VLOOKUP(N13, products, 2, FALSE) -> Meat | P13: Offline | Q13: 1162 | R13: 421.89 | S13: 364.69 | U13: =Q13*R13 -> 490236.18 | V13: =Q13*S13 -> 423769.78 | W13: =U13-V13 -> 66466.4
A14: 104245078 | B14: 41360 | C14: =YEAR(B14) -> 2013 | D14: =TEXT(B14,"MM - MMM") -> 03 - Mar | E14: =CHOOSE(WEEKDAY(B14,2),"Mon","Tue","Wed","Thu","Fri","Sat","Sun") -> Wed | F14: =MATCH(E14,{"Mon","Tue","Wed","Thu","Fri","Sat","Sun"}, 0) -> 3 | G14: 41385 | H14: =(DATEDIF(B14,G14,"D")) -> 25 | I14: M | J14: GBR | K14: =VLOOKUP(J14,countries,2,false) -> United Kingdom | L14: =VLOOKUP($J14,countries,5,false) -> Europe | M14: =VLOOKUP($J14,countries,6,false) -> Northern Europe | N14: 4594 | O14: =VLOOKUP(N14, products, 2, FALSE) -> Fruits | P14: Offline | Q14: 7290 | R14: 9.33 | S14: 6.92 | U14: =Q14*R14 -> 68015.7 | V14: =Q14*S14 -> 50446.8 | W14: =U14-V14 -> 17568.9
A15: 104548490 | B15: 41640 | C15: =YEAR(B15) -> 2014 | D15: =TEXT(B15,"MM - MMM") -> 01 - Jan | E15: =CHOOSE(WEEKDAY(B15,2),"Mon","Tue","Wed","Thu","Fri","Sat","Sun") -> Wed | F15: =MATCH(E15,{"Mon","Tue","Wed","Thu","Fri","Sat","Sun"}, 0) -> 3 | G15: 41644 | H15: =(DATEDIF(B15,G15,"D")) -> 4 | I15: M | J15: Unknown | K15: Unknown | L15: Unknown | M15: Unknown | N15: 7331 | O15: =VLOOKUP(N15, products, 2, FALSE) -> Baby Food | P15: Online | Q15: 7076 | R15: 255.28 | S15: 159.42 | U15: =Q15*R15 -> 1806361.3 | V15: =Q15*S15 -> 1128055.9 | W15: =U15-V15 -> 678305.36
A16: 105030000 | B16: 42523 | C16: =YEAR(B16) -> 2016 | D16: =TEXT(B16,"MM - MMM") -> 06 - Jun | E16: =CHOOSE(WEEKDAY(B16,2),"Mon","Tue","Wed","Thu","Fri","Sat","Sun") -> Thu | F16: =MATCH(E16,{"Mon","Tue","Wed","Thu","Fri","Sat","Sun"}, 0) -> 4 | G16: 42534 | H16: =(DATEDIF(B16,G16,"D")) -> 11 | I16: C | J16: SVN | K16: =VLOOKUP(J16,countries,2,false) -> Slovenia | L16: =VLOOKUP($J16,countries,5,false) -> Europe | M16: =VLOOKUP($J16,countries,6,false) -> Southern Europe | N16: 2455 | O16: =VLOOKUP(N16, products, 2, FALSE) -> Clothes | P16: Offline | Q16: 9566 | R16: 109.28 | S16: 35.84 | U16: =Q16*R16 -> 1045372.5 | V16: =Q16*S16 -> 342845.44 | W16: =U16-V16 -> 702527.04
A17: 107651269 | B17: 41575 | C17: =YEAR(B17) -> 2013 | D17: =TEXT(B17,"MM - MMM") -> 10 - Oct | E17: =CHOOSE(WEEKDAY(B17,2),"Mon","Tue","Wed","Thu","Fri","Sat","Sun") -> Mon | F17: =MATCH(E17,{"Mon","Tue","Wed","Thu","Fri","Sat","Sun"}, 0) -> 1 | G17: 41589 | H17: =(DATEDIF(B17,G17,"D")) -> 14 | I17: M | J17: HRV | K17: =VLOOKUP(J17,countries,2,false) -> Croatia | L17: =VLOOKUP($J17,countries,5,false) -> Europe | M17: =VLOOKUP($J17,countries,6,false) -> Southern Europe | N17: 7940 | O17: =VLOOKUP(N17, products, 2, FALSE) -> Household | P17: Online | Q17: 5258 | R17: 668.27 | S17: 502.54 | U17: =Q17*R17 -> 3513763.7 | V17: =Q17*S17 -> 2642355.3 | W17: =U17-V17 -> 871408.34
A18: 108407437 | B18: 42054 | C18: =YEAR(B18) -> 2015 | D18: =TEXT(B18,"MM - MMM") -> 02 - Feb | E18: =CHOOSE(WEEKDAY(B18,2),"Mon","Tue","Wed","Thu","Fri","Sat","Sun") -> Thu | F18: =MATCH(E18,{"Mon","Tue","Wed","Thu","Fri","Sat","Sun"}, 0) -> 4 | G18: 42090 | H18: =(DATEDIF(B18,G18,"D")) -> 36 | I18: C | J18: ROU | K18: =VLOOKUP(J18,countries,2,false) -> Romania | L18: =VLOOKUP($J18,countries,5,false) -> Europe | M18: =VLOOKUP($J18,countries,6,false) -> Eastern Europe | N18: 7331 | O18: =VLOOKUP(N18, products, 2, FALSE) -> Baby Food | P18: Offline | Q18: 9025 | R18: 255.28 | S18: 159.42 | U18: =Q18*R18 -> 2303902 | V18: =Q18*S18 -> 1438765.5 | W18: =U18-V18 -> 865136.5
A19: 109914195 | B19: 40980 | C19: =YEAR(B19) -> 2012 | D19: =TEXT(B19,"MM - MMM") -> 03 - Mar | E19: =CHOOSE(WEEKDAY(B19,2),"Mon","Tue","Wed","Thu","Fri","Sat","Sun") -> Mon | F19: =MATCH(E19,{"Mon","Tue","Wed","Thu","Fri","Sat","Sun"}, 0) -> 1 | G19: 41015 | H19: =(DATEDIF(B19,G19,"D")) -> 35 | I19: M | J19: POL | K19: =VLOOKUP(J19,countries,2,false) -> Poland | L19: =VLOOKUP($J19,countries,5,false) -> Europe | M19: =VLOOKUP($J19,countries,6,false) -> Eastern Europe | N19: 2455 | O19: =VLOOKUP(N19, products, 2, FALSE) -> Clothes | P19: Offline | Q19: 4908 | R19: 109.28 | S19: 35.84 | U19: =Q19*R19 -> 536346.24 | V19: =Q19*S19 -> 175902.72 | W19: =U19-V19 -> 360443.52
A20: 111063039 | B20: 41055 | C20: =YEAR(B20) -> 2012 | D20: =TEXT(B20,"MM - MMM") -> 05 - May | E20: =CHOOSE(WEEKDAY(B20,2),"Mon","Tue","Wed","Thu","Fri","Sat","Sun") -> Sat | F20: =MATCH(E20,{"Mon","Tue","Wed","Thu","Fri","Sat","Sun"}, 0) -> 6 | G20: 41103 | H20: =(DATEDIF(B20,G20,"D")) -> 48 | I20: L | J20: LUX | K20: =VLOOKUP(J20,countries,2,false) -> Luxembourg | L20: =VLOOKUP($J20,countries,5,false) -> Europe | M20: =VLOOKUP($J20,countries,6,false) -> Western Europe | N20: 7331 | O20: =VLOOKUP(N20, products, 2, FALSE) -> Baby Food | P20: Online | Q20: 4876 | R20: 255.28 | S20: 159.42 | U20: =Q20*R20 -> 1244745.3 | V20: =Q20*S20 -> 777331.92 | W20: =U20-V20 -> 467413.36
A21: 111246287 | B21: 42895 | C21: =YEAR(B21) -> 2017 | D21: =TEXT(B21,"MM - MMM") -> 06 - Jun | E21: =CHOOSE(WEEKDAY(B21,2),"Mon","Tue","Wed","Thu","Fri","Sat","Sun") -> Fri | F21: =MATCH(E21,{"Mon","Tue","Wed","Thu","Fri","Sat","Sun"}, 0) -> 5 | G21: 42918 | H21: =(DATEDIF(B21,G21,"D")) -> 23 | I21: M | J21: CYP | K21: =VLOOKUP(J21,countries,2,false) -> Cyprus | L21: =VLOOKUP($J21,countries,5,false) -> Asia | M21: =VLOOKUP($J21,countries,6,false) -> Western Asia | N21: 8875 | O21: =VLOOKUP(N21, products, 2, FALSE) -> Meat | P21: Offline | Q21: 9103 | R21: 421.89 | S21: 364.69 | U21: =Q21*R21 -> 3840464.7 | V21: =Q21*S21 -> 3319773.1 | W21: =U21-V21 -> 520691.6
A22: 111496055 | B22: 40661 | C22: =YEAR(B22) -> 2011 | D22: =TEXT(B22,"MM - MMM") -> 04 - Apr | E22: =CHOOSE(WEEKDAY(B22,2),"Mon","Tue","Wed","Thu","Fri","Sat","Sun") -> Thu | F22: =MATCH(E22,{"Mon","Tue","Wed","Thu","Fri","Sat","Sun"}, 0) -> 4 | G22: 40698 | H22: =(DATEDIF(B22,G22,"D")) -> 37 | I22: M | J22: BEL | K22: =VLOOKUP(J22,countries,2,false) -> Belgium | L22: =VLOOKUP($J22,countries,5,false) -> Europe | M22: =VLOOKUP($J22,countries,6,false) -> Western Europe | N22: 4594 | O22: =VLOOKUP(N22, products, 2, FALSE) -> Fruits | P22: Online | Q22: 3015 | R22: 9.33 | S22: 6.92 | U22: =Q22*R22 -> 28129.95 | V22: =Q22*S22 -> 20863.8 | W22: =U22-V22 -> 7266.15
A23: 111893022 | B23: 42671 | C23: =YEAR(B23) -> 2016 | D23: =TEXT(B23,"MM - MMM") -> 10 - Oct | E23: =CHOOSE(WEEKDAY(B23,2),"Mon","Tue","Wed","Thu","Fri","Sat","Sun") -> Fri | F23: =MATCH(E23,{"Mon","Tue","Wed","Thu","Fri","Sat","Sun"}, 0) -> 5 | G23: 42706 | H23: =(DATEDIF(B23,G23,"D")) -> 35 | I23: L | J23: SVN | K23: =VLOOKUP(J23,countries,2,false) -> Slovenia | L23: =VLOOKUP($J23,countries,5,false) -> Europe | M23: =VLOOKUP($J23,countries,6,false) -> Southern Europe | N23: 7331 | O23: =VLOOKUP(N23, products, 2, FALSE) -> Baby Food | P23: Online | Q23: 486 | R23: 255.28 | S23: 159.42 | U23: =Q23*R23 -> 124066.08 | V23: =Q23*S23 -> 77478.12 | W23: =U23-V23 -> 46587.96
A24: 112330758 | B24: 42719 | C24: =YEAR(B24) -> 2016 | D24: =TEXT(B24,"MM - MMM") -> 12 - Dec | E24: =CHOOSE(WEEKDAY(B24,2),"Mon","Tue","Wed","Thu","Fri","Sat","Sun") -> Thu | F24: =MATCH(E24,{"Mon","Tue","Wed","Thu","Fri","Sat","Sun"}, 0) -> 4 | G24: 42746 | H24: =(DATEDIF(B24,G24,"D")) -> 27 | I24: C | J24: LTU | K24: =VLOOKUP(J24,countries,2,false) -> Lithuania | L24: =VLOOKUP($J24,countries,5,false) -> Europe | M24: =VLOOKUP($J24,countries,6,false) -> Northern Europe | N24: 8681 | O24: =VLOOKUP(N24, products, 2, FALSE) -> Office Supplies | P24: Offline | Q24: 22 | R24: 651.21 | S24: 524.96 | U24: =Q24*R24 -> 14326.62 | V24: =Q24*S24 -> 11549.12 | W24: =U24-V24 -> 2777.5
A25: 113524663 | B25: 40480 | C25: =YEAR(B25) -> 2010 | D25: =TEXT(B25,"MM - MMM") -> 10 - Oct | E25: =CHOOSE(WEEKDAY(B25,2),"Mon","Tue","Wed","Thu","Fri","Sat","Sun") -> Fri | F25: =MATCH(E25,{"Mon","Tue","Wed","Thu","Fri","Sat","Sun"}, 0) -> 5 | G25: 40521 | H25: =(DATEDIF(B25,G25,"D")) -> 41 | I25: L | J25: RUS | K25: =VLOOKUP(J25,countries,2,false) -> Russia | L25: =VLOOKUP($J25,countries,5,false) -> Europe | M25: =VLOOKUP($J25,countries,6,false) -> Eastern Europe | N25: 8293 | O25: =VLOOKUP(N25, products, 2, FALSE) -> Cosmetics | P25: Online | Q25: 3325 | R25: 437.2 | S25: 263.33 | U25: =Q25*R25 -> 1453690 | V25: =Q25*S25 -> 875572.25 | W25: =U25-V25 -> 578117.75
A26: 114954173 | B26: 40212 | C26: =YEAR(B26) -> 2010 | D26: =TEXT(B26,"MM - MMM") -> 02 - Feb | E26: =CHOOSE(WEEKDAY(B26,2),"Mon","Tue","Wed","Thu","Fri","Sat","Sun") -> Wed | F26: =MATCH(E26,{"Mon","Tue","Wed","Thu","Fri","Sat","Sun"}, 0) -> 3 | G26: 40220 | H26: =(DATEDIF(B26,G26,"D")) -> 8 | I26: C | J26: MLT | K26: =VLOOKUP(J26,countries,2,false) -> Malta | L26: =VLOOKUP($J26,countries,5,false) -> Europe | M26: =VLOOKUP($J26,countries,6,false) -> Southern Europe | N26: 4594 | O26: =VLOOKUP(N26, products, 2, FALSE) -> Fruits | P26: Offline | Q26: 6349 | R26: 9.33 | S26: 6.92 | U26: =Q26*R26 -> 59236.17 | V26: =Q26*S26 -> 43935.08 | W26: =U26-V26 -> 15301.09
A27: 115363156 | B27: 42342 | C27: =YEAR(B27) -> 2015 | D27: =TEXT(B27,"MM - MMM") -> 12 - Dec | E27: =CHOOSE(WEEKDAY(B27,2),"Mon","Tue","Wed","Thu","Fri","Sat","Sun") -> Fri | F27: =MATCH(E27,{"Mon","Tue","Wed","Thu","Fri","Sat","Sun"}, 0) -> 5 | G27: 42379 | H27: =(DATEDIF(B27,G27,"D")) -> 37 | I27: H | J27: UKR | K27: =VLOOKUP(J27,countries,2,false) -> Ukraine | L27: =VLOOKUP($J27,countries,5,false) -> Europe | M27: =VLOOKUP($J27,countries,6,false) -> Eastern Europe | N27: 8681 | O27: =VLOOKUP(N27, products, 2, FALSE) -> Office Supplies | P27: Offline | Q27: 7376 | R27: 651.21 | S27: 524.96 | U27: =Q27*R27 -> 4803325 | V27: =Q27*S27 -> 3872105 | W27: =U27-V27 -> 931220
A28: 117929494 | B28: 42028 | C28: =YEAR(B28) -> 2015 | D28: =TEXT(B28,"MM - MMM") -> 01 - Jan | E28: =CHOOSE(WEEKDAY(B28,2),"Mon","Tue","Wed","Thu","Fri","Sat","Sun") -> Sat | F28: =MATCH(E28,{"Mon","Tue","Wed","Thu","Fri","Sat","Sun"}, 0) -> 6 | G28: 42065 | H28: =(DATEDIF(B28,G28,"D")) -> 37 | I28: H | J28: Unknown | K28: Unknown | L28: Unknown | M28: Unknown | N28: 4594 | O28: =VLOOKUP(N28, products, 2, FALSE) -> Fruits | P28: Offline | Q28: 6813 | R28: 9.33 | S28: 6.92 | U28: =Q28*R28 -> 63565.29 | V28: =Q28*S28 -> 47145.96 | W28: =U28-V28 -> 16419.33
A29: 118086564 | B29: 42419 | C29: =YEAR(B29) -> 2016 | D29: =TEXT(B29,"MM - MMM") -> 02 - Feb | E29: =CHOOSE(WEEKDAY(B29,2),"Mon","Tue","Wed","Thu","Fri","Sat","Sun") -> Fri | F29: =MATCH(E29,{"Mon","Tue","Wed","Thu","Fri","Sat","Sun"}, 0) -> 5 | G29: 42442 | H29: =(DATEDIF(B29,G29,"D")) -> 23 | I29: M | J29: NOR | K29: =VLOOKUP(J29,countries,2,false) -> Norway | L29: =VLOOKUP($J29,countries,5,false) -> Europe | M29: =VLOOKUP($J29,countries,6,false) -> Northern Europe | N29: 8969 | O29: =VLOOKUP(N29, products, 2, FALSE) -> Snacks | P29: Online | Q29: 3293 | R29: 152.58 | S29: 97.44 | U29: =Q29*R29 -> 502445.94 | V29: =Q29*S29 -> 320869.92 | W29: =U29-V29 -> 181576.02
A30: 118659913 | B30: 41853 | C30: =YEAR(B30) -> 2014 | D30: =TEXT(B30,"MM - MMM") -> 08 - Aug | E30: =CHOOSE(WEEKDAY(B30,2),"Mon","Tue","Wed","Thu","Fri","Sat","Sun") -> Sat | F30: =MATCH(E30,{"Mon","Tue","Wed","Thu","Fri","Sat","Sun"}, 0) -> 6 | G30: 41868 | H30: =(DATEDIF(B30,G30,"D")) -> 15 | I30: C | J30: CZE | K30: =VLOOKUP(J30,countries,2,false) -> Czech Republic | L30: =VLOOKUP($J30,countries,5,false) -> Europe | M30: =VLOOKUP($J30,countries,6,false) -> Eastern Europe | N30: 2103 | O30: =VLOOKUP(N30, products, 2, FALSE) -> Cereal | P30: Online | Q30: 2960 | R30: 205.7 | S30: 117.11 | U30: =Q30*R30 -> 608872 | V30: =Q30*S30 -> 346645.6 | W30: =U30-V30 -> 262226.4
A31: 118859469 | B31: 40696 | C31: =YEAR(B31) -> 2011 | D31: =TEXT(B31,"MM - MMM") -> 06 - Jun | E31: =CHOOSE(WEEKDAY(B31,2),"Mon","Tue","Wed","Thu","Fri","Sat","Sun") -> Thu | F31: =MATCH(E31,{"Mon","Tue","Wed","Thu","Fri","Sat","Sun"}, 0) -> 4 | G31: 40725 | H31: =(DATEDIF(B31,G31,"D")) -> 29 | I31: L | J31: Unknown | K31: Unknown | L31: Unknown | M31: Unknown | N31: 8969 | O31: =VLOOKUP(N31, products, 2, FALSE) -> Snacks | P31: Offline | Q31: 2013 | R31: 152.58 | S31: 97.44 | U31: =Q31*R31 -> 307143.54 | V31: =Q31*S31 -> 196146.72 | W31: =U31-V31 -> 110996.82
A32: 119935786 | B32: 42018 | C32: =YEAR(B32) -> 2015 | D32: =TEXT(B32,"MM - MMM") -> 01 - Jan | E32: =CHOOSE(WEEKDAY(B32,2),"Mon","Tue","Wed","Thu","Fri","Sat","Sun") -> Wed | F32: =MATCH(E32,{"Mon","Tue","Wed","Thu","Fri","Sat","Sun"}, 0) -> 3 | G32: 42031 | H32: =(DATEDIF(B32,G32,"D")) -> 13 | I32: L | J32: ROU | K32: =VLOOKUP(J32,countries,2,false) -> Romania | L32: =VLOOKUP($J32,countries,5,false) -> Europe | M32: =VLOOKUP($J32,countries,6,false) -> Eastern Europe | N32: 3127 | O32: =VLOOKUP(N32, products, 2, FALSE) -> Personal Care | P32: Offline | Q32: 519 | R32: 81.73 | S32: 56.67 | U32: =Q32*R32 -> 42417.87 | V32: =Q32*S32 -> 29411.73 | W32: =U32-V32 -> 13006.14
A33: 120419871 | B33: 42137 | C33: =YEAR(B33) -> 2015 | D33: =TEXT(B33,"MM - MMM") -> 05 - May | E33: =CHOOSE(WEEKDAY(B33,2),"Mon","Tue","Wed","Thu","Fri","Sat","Sun") -> Wed | F33: =MATCH(E33,{"Mon","Tue","Wed","Thu","Fri","Sat","Sun"}, 0) -> 3 | G33: 42181 | H33: =(DATEDIF(B33,G33,"D")) -> 44 | I33: H | J33: LTU | K33: =VLOOKUP(J33,countries,2,false) -> Lithuania | L33: =VLOOKUP($J33,countries,5,false) -> Europe | M33: =VLOOKUP($J33,countries,6,false) -> Northern Europe | N33: 3127 | O33: =VLOOKUP(N33, products, 2, FALSE) -> Personal Care | P33: Online | Q33: 3771 | R33: 81.73 | S33: 56.67 | U33: =Q33*R33 -> 308203.83 | V33: =Q33*S33 -> 213702.57 | W33: =U33-V33 -> 94501.26
A34: 120977771 | B34: 40625 | C34: =YEAR(B34) -> 2011 | D34: =TEXT(B34,"MM - MMM") -> 03 - Mar | E34: =CHOOSE(WEEKDAY(B34,2),"Mon","Tue","Wed","Thu","Fri","Sat","Sun") -> Wed | F34: =MATCH(E34,{"Mon","Tue","Wed","Thu","Fri","Sat","Sun"}, 0) -> 3 | G34: 40665 | H34: =(DATEDIF(B34,G34,"D")) -> 40 | I34: M | J34: ARM | K34: =VLOOKUP(J34,countries,2,false) -> Armenia | L34: =VLOOKUP($J34,countries,5,false) -> Asia | M34: =VLOOKUP($J34,countries,6,false) -> Western Asia | N34: 4594 | O34: =VLOOKUP(N34, products, 2, FALSE) -> Fruits | P34: Online | Q34: 8866 | R34: 9.33 | S34: 6.92 | U34: =Q34*R34 -> 82719.78 | V34: =Q34*S34 -> 61352.72 | W34: =U34-V34 -> 21367.06
A35: 121380746 | B35: 42695 | C35: =YEAR(B35) -> 2016 | D35: =TEXT(B35,"MM - MMM") -> 11 - Nov | E35: =CHOOSE(WEEKDAY(B35,2),"Mon","Tue","Wed","Thu","Fri","Sat","Sun") -> Mon | F35: =MATCH(E35,{"Mon","Tue","Wed","Thu","Fri","Sat","Sun"}, 0) -> 1 | G35: 42722 | H35: =(DATEDIF(B35,G35,"D")) -> 27 | I35: C | J35: MLT | K35: =VLOOKUP(J35,countries,2,false) -> Malta | L35: =VLOOKUP($J35,countries,5,false) -> Europe | M35: =VLOOKUP($J35,countries,6,false) -> Southern Europe | N35: 4594 | O35: =VLOOKUP(N35, products, 2, FALSE) -> Fruits | P35: Online | Q35: 8115 | R35: 9.33 | S35: 6.92 | U35: =Q35*R35 -> 75712.95 | V35: =Q35*S35 -> 56155.8 | W35: =U35-V35 -> 19557.15
A36: 121945512 | B36: 42833 | C36: =YEAR(B36) -> 2017 | D36: =TEXT(B36,"MM - MMM") -> 04 - Apr | E36: =CHOOSE(WEEKDAY(B36,2),"Mon","Tue","Wed","Thu","Fri","Sat","Sun") -> Sat | F36: =MATCH(E36,{"Mon","Tue","Wed","Thu","Fri","Sat","Sun"}, 0) -> 6 | G36: 42837 | H36: =(DATEDIF(B36,G36,"D")) -> 4 | I36: C | J36: GBR | K36: =VLOOKUP(J36,countries,2,false) -> United Kingdom | L36: =VLOOKUP($J36,countries,5,false) -> Europe | M36: =VLOOKUP($J36,countries,6,false) -> Northern Europe | N36: 1270 | O36: =VLOOKUP(N36, products, 2, FALSE) -> Beverages | P36: Online | Q36: 5242 | R36: 47.45 | S36: 31.79 | U36: =Q36*R36 -> 248732.9 | V36: =Q36*S36 -> 166643.18 | W36: =U36-V36 -> 82089.72
A37: 122144210 | B37: 42852 | C37: =YEAR(B37) -> 2017 | D37: =TEXT(B37,"MM - MMM") -> 04 - Apr | E37: =CHOOSE(WEEKDAY(B37,2),"Mon","Tue","Wed","Thu","Fri","Sat","Sun") -> Thu | F37: =MATCH(E37,{"Mon","Tue","Wed","Thu","Fri","Sat","Sun"}, 0) -> 4 | G37: 42879 | H37: =(DATEDIF(B37,G37,"D")) -> 27 | I37: C | J37: MNE | K37: =VLOOKUP(J37,countries,2,false) -> Montenegro | L37: =VLOOKUP($J37,countries,5,false) -> Europe | M37: =VLOOKUP($J37,countries,6,false) -> Southern Europe | N37: 1270 | O37: =VLOOKUP(N37, products, 2, FALSE) -> Beverages | P37: Offline | Q37: 4041 | R37: 47.45 | S37: 31.79 | U37: =Q37*R37 -> 191745.45 | V37: =Q37*S37 -> 128463.39 | W37: =U37-V37 -> 63282.06
A38: 122372519 | B38: 42379 | C38: =YEAR(B38) -> 2016 | D38: =TEXT(B38,"MM - MMM") -> 01 - Jan | E38: =CHOOSE(WEEKDAY(B38,2),"Mon","Tue","Wed","Thu","Fri","Sat","Sun") -> Sun | F38: =MATCH(E38,{"Mon","Tue","Wed","Thu","Fri","Sat","Sun"}, 0) -> 7 | G38: 42382 | H38: =(DATEDIF(B38,G38,"D")) -> 3 | I38: L | J38: PRT | K38: =VLOOKUP(J38,countries,2,false) -> Portugal | L38: =VLOOKUP($J38,countries,5,false) -> Europe | M38: =VLOOKUP($J38,countries,6,false) -> Southern Europe | N38: 1270 | O38: =VLOOKUP(N38, products, 2, FALSE) -> Beverages | P38: Offline | Q38: 1603 | R38: 47.45 | S38: 31.79 | U38: =Q38*R38 -> 76062.35 | V38: =Q38*S38 -> 50959.37 | W38: =U38-V38 -> 25102.98
A39: 122967326 | B39: 42818 | C39: =YEAR(B39) -> 2017 | D39: =TEXT(B39,"MM - MMM") -> 03 - Mar | E39: =CHOOSE(WEEKDAY(B39,2),"Mon","Tue","Wed","Thu","Fri","Sat","Sun") -> Fri | F39: =MATCH(E39,{"Mon","Tue","Wed","Thu","Fri","Sat","Sun"}, 0) -> 5 | G39: 42850 | H39: =(DATEDIF(B39,G39,"D")) -> 32 | I39: H | J39: BLR | K39: =VLOOKUP(J39,countries,2,false) -> Belarus | L39: =VLOOKUP($J39,countries,5,false) -> Europe | M39: =VLOOKUP($J39,countries,6,false) -> Eastern Europe | N39: 1270 | O39: =VLOOKUP(N39, products, 2, FALSE) -> Beverages | P39: Online | Q39: 7619 | R39: 47.45 | S39: 31.79 | U39: =Q39*R39 -> 361521.55 | V39: =Q39*S39 -> 242208.01 | W39: =U39-V39 -> 119313.54
A40: 123086202 | B40: 41641 | C40: =YEAR(B40) -> 2014 | D40: =TEXT(B40,"MM - MMM") -> 01 - Jan | E40: =CHOOSE(WEEKDAY(B40,2),"Mon","Tue","Wed","Thu","Fri","Sat","Sun") -> Thu | F40: =MATCH(E40,{"Mon","Tue","Wed","Thu","Fri","Sat","Sun"}, 0) -> 4 | G40: 41690 | H40: =(DATEDIF(B40,G40,"D")) -> 49 | I40: M | J40: EST | K40: =VLOOKUP(J40,countries,2,false) -> Estonia | L40: =VLOOKUP($J40,countries,5,false) -> Europe | M40: =VLOOKUP($J40,countries,6,false) -> Northern Europe | N40: 7331 | O40: =VLOOKUP(N40, products, 2, FALSE) -> Baby Food | P40: Offline | Q40: 2797 | R40: 255.28 | S40: 159.42 | U40: =Q40*R40 -> 714018.16 | V40: =Q40*S40 -> 445897.74 | W40: =U40-V40 -> 268120.42
A41: 123544108 | B41: 40311 | C41: =YEAR(B41) -> 2010 | D41: =TEXT(B41,"MM - MMM") -> 05 - May | E41: =CHOOSE(WEEKDAY(B41,2),"Mon","Tue","Wed","Thu","Fri","Sat","Sun") -> Thu | F41: =MATCH(E41,{"Mon","Tue","Wed","Thu","Fri","Sat","Sun"}, 0) -> 4 | G41: 40351 | H41: =(DATEDIF(B41,G41,"D")) -> 40 | I41: M | J41: AUT | K41: =VLOOKUP(J41,countries,2,false) -> Austria | L41: =VLOOKUP($J41,countries,5,false) -> Europe | M41: =VLOOKUP($J41,countries,6,false) -> Western Europe | N41: 2103 | O41: =VLOOKUP(N41, products, 2, FALSE) -> Cereal | P41: Online | Q41: 8302 | R41: 205.7 | S41: 117.11 | U41: =Q41*R41 -> 1707721.4 | V41: =Q41*S41 -> 972247.22 | W41: =U41-V41 -> 735474.18
A42: 123938930 | B42: 41114 | C42: =YEAR(B42) -> 2012 | D42: =TEXT(B42,"MM - MMM") -> 07 - Jul | E42: =CHOOSE(WEEKDAY(B42,2),"Mon","Tue","Wed","Thu","Fri","Sat","Sun") -> Tue | F42: =MATCH(E42,{"Mon","Tue","Wed","Thu","Fri","Sat","Sun"}, 0) -> 2 | G42: 41123 | H42: =(DATEDIF(B42,G42,"D")) -> 9 | I42: M | J42: BLR | K42: =VLOOKUP(J42,countries,2,false) -> Belarus | L42: =VLOOKUP($J42,countries,5,false) -> Europe | M42: =VLOOKUP($J42,countries,6,false) -> Eastern Europe | N42: 1270 | O42: =VLOOKUP(N42, products, 2, FALSE) -> Beverages | P42: Online | Q42: 5138 | R42: 47.45 | S42: 31.79 | U42: =Q42*R42 -> 243798.1 | V42: =Q42*S42 -> 163337.02 | W42: =U42-V42 -> 80461.08
A43: 125339686 | B43: 42927 | C43: =YEAR(B43) -> 2017 | D43: =TEXT(B43,"MM - MMM") -> 07 - Jul | E43: =CHOOSE(WEEKDAY(B43,2),"Mon","Tue","Wed","Thu","Fri","Sat","Sun") -> Tue | F43: =MATCH(E43,{"Mon","Tue","Wed","Thu","Fri","Sat","Sun"}, 0) -> 2 | G43: 42940 | H43: =(DATEDIF(B43,G43,"D")) -> 13 | I43: L | J43: MKD | K43: =VLOOKUP(J43,countries,2,false) -> Macedonia | L43: =VLOOKUP($J43,countries,5,false) -> Europe | M43: =VLOOKUP($J43,countries,6,false) -> Southern Europe | N43: 8969 | O43: =VLOOKUP(N43, products, 2, FALSE) -> Snacks | P43: Online | Q43: 9653 | R43: 152.58 | S43: 97.44 | U43: =Q43*R43 -> 1472854.7 | V43: =Q43*S43 -> 940588.32 | W43: =U43-V43 -> 532266.42
A44: 125349128 | B44: 41047 | C44: =YEAR(B44) -> 2012 | D44: =TEXT(B44,"MM - MMM") -> 05 - May | E44: =CHOOSE(WEEKDAY(B44,2),"Mon","Tue","Wed","Thu","Fri","Sat","Sun") -> Fri | F44: =MATCH(E44,{"Mon","Tue","Wed","Thu","Fri","Sat","Sun"}, 0) -> 5 | G44: 41066 | H44: =(DATEDIF(B44,G44,"D")) -> 19 | I44: L | J44: SMR | K44: =VLOOKUP(J44,countries,2,false) -> San Marino | L44: =VLOOKUP($J44,countries,5,false) -> Europe | M44: =VLOOKUP($J44,countries,6,false) -> Southern Europe | N44: 2103 | O44: =VLOOKUP(N44, products, 2, FALSE) -> Cereal | P44: Offline | Q44: 2447 | R44: 205.7 | S44: 117.11 | U44: =Q44*R44 -> 503347.9 | V44: =Q44*S44 -> 286568.17 | W44: =U44-V44 -> 216779.73
A45: 126948583 | B45: 42879 | C45: =YEAR(B45) -> 2017 | D45: =TEXT(B45,"MM - MMM") -> 05 - May | E45: =CHOOSE(WEEKDAY(B45,2),"Mon","Tue","Wed","Thu","Fri","Sat","Sun") -> Wed | F45: =MATCH(E45,{"Mon","Tue","Wed","Thu","Fri","Sat","Sun"}, 0) -> 3 | G45: 42925 | H45: =(DATEDIF(B45,G45,"D")) -> 46 | I45: C | J45: Unknown | K45: Unknown | L45: Unknown | M45: Unknown | N45: 7331 | O45: =VLOOKUP(N45, products, 2, FALSE) -> Baby Food | P45: Online | Q45: 5762 | R45: 255.28 | S45: 159.42 | U45: =Q45*R45 -> 1470923.4 | V45: =Q45*S45 -> 918578.04 | W45: =U45-V45 -> 552345.32
A46: 127694451 | B46: 40884 | C46: =YEAR(B46) -> 2011 | D46: =TEXT(B46,"MM - MMM") -> 12 - Dec | E46: =CHOOSE(WEEKDAY(B46,2),"Mon","Tue","Wed","Thu","Fri","Sat","Sun") -> Wed | F46: =MATCH(E46,{"Mon","Tue","Wed","Thu","Fri","Sat","Sun"}, 0) -> 3 | G46: 40904 | H46: =(DATEDIF(B46,G46,"D")) -> 20 | I46: L | J46: EST | K46: =VLOOKUP(J46,countries,2,false) -> Estonia | L46: =VLOOKUP($J46,countries,5,false) -> Europe | M46: =VLOOKUP($J46,countries,6,false) -> Northern Europe | N46: 5988 | O46: =VLOOKUP(N46, products, 2, FALSE) -> Vegetables | P46: Offline | Q46: 6481 | R46: 154.06 | S46: 90.93 | U46: =Q46*R46 -> 998462.86 | V46: =Q46*S46 -> 589317.33 | W46: =U46-V46 -> 409145.53
A47: 127838218 | B47: 41537 | C47: =YEAR(B47) -> 2013 | D47: =TEXT(B47,"MM - MMM") -> 09 - Sep | E47: =CHOOSE(WEEKDAY(B47,2),"Mon","Tue","Wed","Thu","Fri","Sat","Sun") -> Fri | F47: =MATCH(E47,{"Mon","Tue","Wed","Thu","Fri","Sat","Sun"}, 0) -> 5 | G47: 41576 | H47: =(DATEDIF(B47,G47,"D")) -> 39 | I47: C | J47: NLD | K47: =VLOOKUP(J47,countries,2,false) -> Netherlands | L47: =VLOOKUP($J47,countries,5,false) -> Europe | M47: =VLOOKUP($J47,countries,6,false) -> Western Europe | N47: 4594 | O47: =VLOOKUP(N47, products, 2, FALSE) -> Fruits | P47: Offline | Q47: 9024 | R47: 9.33 | S47: 6.92 | U47: =Q47*R47 -> 84193.92 | V47: =Q47*S47 -> 62446.08 | W47: =U47-V47 -> 21747.84
A48: 128003442 | B48: 40430 | C48: =YEAR(B48) -> 2010 | D48: =TEXT(B48,"MM - MMM") -> 09 - Sep | E48: =CHOOSE(WEEKDAY(B48,2),"Mon","Tue","Wed","Thu","Fri","Sat","Sun") -> Thu | F48: =MATCH(E48,{"Mon","Tue","Wed","Thu","Fri","Sat","Sun"}, 0) -> 4 | G48: 40474 | H48: =(DATEDIF(B48,G48,"D")) -> 44 | I48: L | J48: CHE | K48: =VLOOKUP(J48,countries,2,false) -> Switzerland | L48: =VLOOKUP($J48,countries,5,false) -> Europe | M48: =VLOOKUP($J48,countries,6,false) -> Western Europe | N48: 7331 | O48: =VLOOKUP(N48, products, 2, FALSE) -> Baby Food | P48: Online | Q48: 7918 | R48: 255.28 | S48: 159.42 | U48: =Q48*R48 -> 2021307 | V48: =Q48*S48 -> 1262287.6 | W48: =U48-V48 -> 759019.48
A49: 128686225 | B49: 40568 | C49: =YEAR(B49) -> 2011 | D49: =TEXT(B49,"MM - MMM") -> 01 - Jan | E49: =CHOOSE(WEEKDAY(B49,2),"Mon","Tue","Wed","Thu","Fri","Sat","Sun") -> Tue | F49: =MATCH(E49,{"Mon","Tue","Wed","Thu","Fri","Sat","Sun"}, 0) -> 2 | G49: 40615 | H49: =(DATEDIF(B49,G49,"D")) -> 47 | I49: M | J49: HUN | K49: =VLOOKUP(J49,countries,2,false) -> Hungary | L49: =VLOOKUP($J49,countries,5,false) -> Europe | M49: =VLOOKUP($J49,countries,6,false) -> Eastern Europe | N49: 7331 | O49: =VLOOKUP(N49, products, 2, FALSE) -> Baby Food | P49: Online | Q49: 9968 | R49: 255.28 | S49: 159.42 | U49: =Q49*R49 -> 2544631 | V49: =Q49*S49 -> 1589098.6 | W49: =U49-V49 -> 955532.48
A50: 128766906 | B50: 40587 | C50: =YEAR(B50) -> 2011 | D50: =TEXT(B50,"MM - MMM") -> 02 - Feb | E50: =CHOOSE(WEEKDAY(B50,2),"Mon","Tue","Wed","Thu","Fri","Sat","Sun") -> Sun | F50: =MATCH(E50,{"Mon","Tue","Wed","Thu","Fri","Sat","Sun"}, 0) -> 7 | G50: 40630 | H50: =(DATEDIF(B50,G50,"D")) -> 43 | I50: C | J50: Unknown | K50: Unknown | L50: Unknown | M50: Unknown | N50: 7940 | O50: =VLOOKUP(N50, products, 2, FALSE) -> Household | P50: Offline | Q50: 3844 | R50: 668.27 | S50: 502.54 | U50: =Q50*R50 -> 2568829.9 | V50: =Q50*S50 -> 1931763.8 | W50: =U50-V50 -> 637066.12
A51: 129127395 | B51: 41441 | C51: =YEAR(B51) -> 2013 | D51: =TEXT(B51,"MM - MMM") -> 06 - Jun | E51: =CHOOSE(WEEKDAY(B51,2),"Mon","Tue","Wed","Thu","Fri","Sat","Sun") -> Sun | F51: =MATCH(E51,{"Mon","Tue","Wed","Thu","Fri","Sat","Sun"}, 0) -> 7 | G51: 41445 | H51: =(DATEDIF(B51,G51,"D")) -> 4 | I51: L | J51: LVA | K51: =VLOOKUP(J51,countries,2,false) -> Latvia | L51: =VLOOKUP($J51,countries,5,false) -> Europe | M51: =VLOOKUP($J51,countries,6,false) -> Northern Europe | N51: 8681 | O51: =VLOOKUP(N51, products, 2, FALSE) -> Office Supplies | P51: Online | Q51: 520 | R51: 651.21 | S51: 524.96 | U51: =Q51*R51 -> 338629.2 | V51: =Q51*S51 -> 272979.2 | W51: =U51-V51 -> 65650
A52: 129169023 | B52: 41068 | C52: =YEAR(B52) -> 2012 | D52: =TEXT(B52,"MM - MMM") -> 06 - Jun | E52: =CHOOSE(WEEKDAY(B52,2),"Mon","Tue","Wed","Thu","Fri","Sat","Sun") -> Fri | F52: =MATCH(E52,{"Mon","Tue","Wed","Thu","Fri","Sat","Sun"}, 0) -> 5 | G52: 41108 | H52: =(DATEDIF(B52,G52,"D")) -> 40 | I52: M | J52: Unknown | K52: Unknown | L52: Unknown | M52: Unknown | N52: 1270 | O52: =VLOOKUP(N52, products, 2, FALSE) -> Beverages | P52: Offline | Q52: 2839 | R52: 47.45 | S52: 31.79 | U52: =Q52*R52 -> 134710.55 | V52: =Q52*S52 -> 90251.81 | W52: =U52-V52 -> 44458.74
A53: 129875409 | B53: 40652 | C53: =YEAR(B53) -> 2011 | D53: =TEXT(B53,"MM - MMM") -> 04 - Apr | E53: =CHOOSE(WEEKDAY(B53,2),"Mon","Tue","Wed","Thu","Fri","Sat","Sun") -> Tue | F53: =MATCH(E53,{"Mon","Tue","Wed","Thu","Fri","Sat","Sun"}, 0) -> 2 | G53: 40659 | H53: =(DATEDIF(B53,G53,"D")) -> 7 | I53: L | J53: LTU | K53: =VLOOKUP(J53,countries,2,false) -> Lithuania | L53: =VLOOKUP($J53,countries,5,false) -> Europe | M53: =VLOOKUP($J53,countries,6,false) -> Northern Europe | N53: 3127 | O53: =VLOOKUP(N53, products, 2, FALSE) -> Personal Care | P53: Offline | Q53: 1875 | R53: 81.73 | S53: 56.67 | U53: =Q53*R53 -> 153243.75 | V53: =Q53*S53 -> 106256.25 | W53: =U53-V53 -> 46987.5
A54: 129902875 | B54: 41719 | C54: =YEAR(B54) -> 2014 | D54: =TEXT(B54,"MM - MMM") -> 03 - Mar | E54: =CHOOSE(WEEKDAY(B54,2),"Mon","Tue","Wed","Thu","Fri","Sat","Sun") -> Fri | F54: =MATCH(E54,{"Mon","Tue","Wed","Thu","Fri","Sat","Sun"}, 0) -> 5 | G54: 41753 | H54: =(DATEDIF(B54,G54,"D")) -> 34 | I54: C | J54: BGR | K54: =VLOOKUP(J54,countries,2,false) -> Bulgaria | L54: =VLOOKUP($J54,countries,5,false) -> Europe | M54: =VLOOKUP($J54,countries,6,false) -> Eastern Europe | N54: 7940 | O54: =VLOOKUP(N54, products, 2, FALSE) -> Household | P54: Online | Q54: 2 | R54: 668.27 | S54: 502.54 | U54: =Q54*R54 -> 1336.54 | V54: =Q54*S54 -> 1005.08 | W54: =U54-V54 -> 331.46
A55: 130356919 | B55: 41535 | C55: =YEAR(B55) -> 2013 | D55: =TEXT(B55,"MM - MMM") -> 09 - Sep | E55: =CHOOSE(WEEKDAY(B55,2),"Mon","Tue","Wed","Thu","Fri","Sat","Sun") -> Wed | F55: =MATCH(E55,{"Mon","Tue","Wed","Thu","Fri","Sat","Sun"}, 0) -> 3 | G55: 41548 | H55: =(DATEDIF(B55,G55,"D")) -> 13 | I55: H | J55: CHE | K55: =VLOOKUP(J55,countries,2,false) -> Switzerland | L55: =VLOOKUP($J55,countries,5,false) -> Europe | M55: =VLOOKUP($J55,countries,6,false) -> Western Europe | N55: 5988 | O55: =VLOOKUP(N55, products, 2, FALSE) -> Vegetables | P55: Online | Q55: 4364 | R55: 154.06 | S55: 90.93 | U55: =Q55*R55 -> 672317.84 | V55: =Q55*S55 -> 396818.52 | W55: =U55-V55 -> 275499.32
A56: 130754315 | B56: 41574 | C56: =YEAR(B56) -> 2013 | D56: =TEXT(B56,"MM - MMM") -> 10 - Oct | E56: =CHOOSE(WEEKDAY(B56,2),"Mon","Tue","Wed","Thu","Fri","Sat","Sun") -> Sun | F56: =MATCH(E56,{"Mon","Tue","Wed","Thu","Fri","Sat","Sun"}, 0) -> 7 | G56: 41580 | H56: =(DATEDIF(B56,G56,"D")) -> 6 | I56: H | J56: FRA | K56: =VLOOKUP(J56,countries,2,false) -> France | L56: =VLOOKUP($J56,countries,5,false) -> Europe | M56: =VLOOKUP($J56,countries,6,false) -> Western Europe | N56: 8681 | O56: =VLOOKUP(N56, products, 2, FALSE) -> Office Supplies | P56: Online | Q56: 1962 | R56: 651.21 | S56: 524.96 | U56: =Q56*R56 -> 1277674 | V56: =Q56*S56 -> 1029971.5 | W56: =U56-V56 -> 247702.5
A57: 131585586 | B57: 42807 | C57: =YEAR(B57) -> 2017 | D57: =TEXT(B57,"MM - MMM") -> 03 - Mar | E57: =CHOOSE(WEEKDAY(B57,2),"Mon","Tue","Wed","Thu","Fri","Sat","Sun") -> Mon | F57: =MATCH(E57,{"Mon","Tue","Wed","Thu","Fri","Sat","Sun"}, 0) -> 1 | G57: 42838 | H57: =(DATEDIF(B57,G57,"D")) -> 31 | I57: C | J57: FRA | K57: =VLOOKUP(J57,countries,2,false) -> France | L57: =VLOOKUP($J57,countries,5,false) -> Europe | M57: =VLOOKUP($J57,countries,6,false) -> Western Europe | N57: 3127 | O57: =VLOOKUP(N57, products, 2, FALSE) -> Personal Care | P57: Offline | Q57: 7954 | R57: 81.73 | S57: 56.67 | U57: =Q57*R57 -> 650080.42 | V57: =Q57*S57 -> 450753.18 | W57: =U57-V57 -> 199327.24
A58: 132069671 | B58: 42925 | C58: =YEAR(B58) -> 2017 | D58: =TEXT(B58,"MM - MMM") -> 07 - Jul | E58: =CHOOSE(WEEKDAY(B58,2),"Mon","Tue","Wed","Thu","Fri","Sat","Sun") -> Sun | F58: =MATCH(E58,{"Mon","Tue","Wed","Thu","Fri","Sat","Sun"}, 0) -> 7 | G58: 42936 | H58: =(DATEDIF(B58,G58,"D")) -> 11 | I58: M | J58: AUT | K58: =VLOOKUP(J58,countries,2,false) -> Austria | L58: =VLOOKUP($J58,countries,5,false) -> Europe | M58: =VLOOKUP($J58,countries,6,false) -> Western Europe | N58: 3127 | O58: =VLOOKUP(N58, products, 2, FALSE) -> Personal Care | P58: Online | Q58: 1205 | R58: 81.73 | S58: 56.67 | U58: =Q58*R58 -> 98484.65 | V58: =Q58*S58 -> 68287.35 | W58: =U58-V58 -> 30197.3
A59: 132603538 | B59: 41172 | C59: =YEAR(B59) -> 2012 | D59: =TEXT(B59,"MM - MMM") -> 09 - Sep | E59: =CHOOSE(WEEKDAY(B59,2),"Mon","Tue","Wed","Thu","Fri","Sat","Sun") -> Thu | F59: =MATCH(E59,{"Mon","Tue","Wed","Thu","Fri","Sat","Sun"}, 0) -> 4 | G59: 41219 | H59: =(DATEDIF(B59,G59,"D")) -> 47 | I59: M | J59: HUN | K59: =VLOOKUP(J59,countries,2,false) -> Hungary | L59: =VLOOKUP($J59,countries,5,false) -> Europe | M59: =VLOOKUP($J59,countries,6,false) -> Eastern Europe | N59: 8293 | O59: =VLOOKUP(N59, products, 2, FALSE) -> Cosmetics | P59: Online | Q59: 9188 | R59: 437.2 | S59: 263.33 | U59: =Q59*R59 -> 4016993.6 | V59: =Q59*S59 -> 2419476 | W59: =U59-V59 -> 1597517.6
A60: 133276450 | B60: 42396 | C60: =YEAR(B60) -> 2016 | D60: =TEXT(B60,"MM - MMM") -> 01 - Jan | E60: =CHOOSE(WEEKDAY(B60,2),"Mon","Tue","Wed","Thu","Fri","Sat","Sun") -> Wed | F60: =MATCH(E60,{"Mon","Tue","Wed","Thu","Fri","Sat","Sun"}, 0) -> 3 | G60: 42444 | H60: =(DATEDIF(B60,G60,"D")) -> 48 | I60: H | J60: Unknown | K60: Unknown | L60: Unknown | M60: Unknown | N60: 3127 | O60: =VLOOKUP(N60, products, 2, FALSE) -> Personal Care | P60: Online | Q60: 8318 | R60: 81.73 | S60: 56.67 | U60: =Q60*R60 -> 679830.14 | V60: =Q60*S60 -> 471381.06 | W60: =U60-V60 -> 208449.08
A61: 134121024 | B61: 40602 | C61: =YEAR(B61) -> 2011 | D61: =TEXT(B61,"MM - MMM") -> 02 - Feb | E61: =CHOOSE(WEEKDAY(B61,2),"Mon","Tue","Wed","Thu","Fri","Sat","Sun") -> Mon | F61: =MATCH(E61,{"Mon","Tue","Wed","Thu","Fri","Sat","Sun"}, 0) -> 1 | G61: 40641 | H61: =(DATEDIF(B61,G61,"D")) -> 39 | I61: L | J61: EST | K61: =VLOOKUP(J61,countries,2,false) -> Estonia | L61: =VLOOKUP($J61,countries,5,false) -> Europe | M61: =VLOOKUP($J61,countries,6,false) -> Northern Europe | N61: 5988 | O61: =VLOOKUP(N61, products, 2, FALSE) -> Vegetables | P61: Online | Q61: 8246 | R61: 154.06 | S61: 90.93 | U61: =Q61*R61 -> 1270378.8 | V61: =Q61*S61 -> 749808.78 | W61: =U61-V61 -> 520569.98
A62: 134790503 | B62: 41001 | C62: =YEAR(B62) -> 2012 | D62: =TEXT(B62,"MM - MMM") -> 04 - Apr | E62: =CHOOSE(WEEKDAY(B62,2),"Mon","Tue","Wed","Thu","Fri","Sat","Sun") -> Mon | F62: =MATCH(E62,{"Mon","Tue","Wed","Thu","Fri","Sat","Sun"}, 0) -> 1 | G62: 41025 | H62: =(DATEDIF(B62,G62,"D")) -> 24 | I62: M | J62: ITA | K62: =VLOOKUP(J62,countries,2,false) -> Italy | L62: =VLOOKUP($J62,countries,5,false) -> Europe | M62: =VLOOKUP($J62,countries,6,false) -> Southern Europe | N62: 2455 | O62: =VLOOKUP(N62, products, 2, FALSE) -> Clothes | P62: Online | Q62: 6360 | R62: 109.28 | S62: 35.84 | U62: =Q62*R62 -> 695020.8 | V62: =Q62*S62 -> 227942.4 | W62: =U62-V62 -> 467078.4
A63: 136624276 | B63: 42420 | C63: =YEAR(B63) -> 2016 | D63: =TEXT(B63,"MM - MMM") -> 02 - Feb | E63: =CHOOSE(WEEKDAY(B63,2),"Mon","Tue","Wed","Thu","Fri","Sat","Sun") -> Sat | F63: =MATCH(E63,{"Mon","Tue","Wed","Thu","Fri","Sat","Sun"}, 0) -> 6 | G63: 42437 | H63: =(DATEDIF(B63,G63,"D")) -> 17 | I63: L | J63: LVA | K63: =VLOOKUP(J63,countries,2,false) -> Latvia | L63: =VLOOKUP($J63,countries,5,false) -> Europe | M63: =VLOOKUP($J63,countries,6,false) -> Northern Europe | N63: 1270 | O63: =VLOOKUP(N63, products, 2, FALSE) -> Beverages | P63: Offline | Q63: 9014 | R63: 47.45 | S63: 31.79 | U63: =Q63*R63 -> 427714.3 | V63: =Q63*S63 -> 286555.06 | W63: =U63-V63 -> 141159.24
A64: 138025033 | B64: 41468 | C64: =YEAR(B64) -> 2013 | D64: =TEXT(B64,"MM - MMM") -> 07 - Jul | E64: =CHOOSE(WEEKDAY(B64,2),"Mon","Tue","Wed","Thu","Fri","Sat","Sun") -> Sat | F64: =MATCH(E64,{"Mon","Tue","Wed","Thu","Fri","Sat","Sun"}, 0) -> 6 | G64: 41489 | H64: =(DATEDIF(B64,G64,"D")) -> 21 | I64: L | J64: GBR | K64: =VLOOKUP(J64,countries,2,false) -> United Kingdom | L64: =VLOOKUP($J64,countries,5,false) -> Europe | M64: =VLOOKUP($J64,countries,6,false) -> Northern Europe | N64: 8969 | O64: =VLOOKUP(N64, products, 2, FALSE) -> Snacks | P64: Online | Q64: 3529 | R64: 152.58 | S64: 97.44 | U64: =Q64*R64 -> 538454.82 | V64: =Q64*S64 -> 343865.76 | W64: =U64-V64 -> 194589.06
A65: 138182103 | B65: 41860 | C65: =YEAR(B65) -> 2014 | D65: =TEXT(B65,"MM - MMM") -> 08 - Aug | E65: =CHOOSE(WEEKDAY(B65,2),"Mon","Tue","Wed","Thu","Fri","Sat","Sun") -> Sat | F65: =MATCH(E65,{"Mon","Tue","Wed","Thu","Fri","Sat","Sun"}, 0) -> 6 | G65: 41867 | H65: =(DATEDIF(B65,G65,"D")) -> 7 | I65: C | J65: NLD | K65: =VLOOKUP(J65,countries,2,false) -> Netherlands | L65: =VLOOKUP($J65,countries,5,false) -> Europe | M65: =VLOOKUP($J65,countries,6,false) -> Western Europe | N65: 8681 | O65: =VLOOKUP(N65, products, 2, FALSE) -> Office Supplies | P65: Online | Q65: 10 | R65: 651.21 | S65: 524.96 | U65: =Q65*R65 -> 6512.1 | V65: =Q65*S65 -> 5249.6 | W65: =U65-V65 -> 1262.5
A66: 138820683 | B66: 40368 | C66: =YEAR(B66) -> 2010 | D66: =TEXT(B66,"MM - MMM") -> 07 - Jul | E66: =CHOOSE(WEEKDAY(B66,2),"Mon","Tue","Wed","Thu","Fri","Sat","Sun") -> Fri | F66: =MATCH(E66,{"Mon","Tue","Wed","Thu","Fri","Sat","Sun"}, 0) -> 5 | G66: 40368 | H66: =(DATEDIF(B66,G66,"D")) -> 0 | I66: L | J66: RUS | K66: =VLOOKUP(J66,countries,2,false) -> Russia | L66: =VLOOKUP($J66,countries,5,false) -> Europe | M66: =VLOOKUP($J66,countries,6,false) -> Eastern Europe | N66: 2455 | O66: =VLOOKUP(N66, products, 2, FALSE) -> Clothes | P66: Offline | Q66: 8980 | R66: 109.28 | S66: 35.84 | U66: =Q66*R66 -> 981334.4 | V66: =Q66*S66 -> 321843.2 | W66: =U66-V66 -> 659491.2
A67: 139201343 | B67: 42609 | C67: =YEAR(B67) -> 2016 | D67: =TEXT(B67,"MM - MMM") -> 08 - Aug | E67: =CHOOSE(WEEKDAY(B67,2),"Mon","Tue","Wed","Thu","Fri","Sat","Sun") -> Sat | F67: =MATCH(E67,{"Mon","Tue","Wed","Thu","Fri","Sat","Sun"}, 0) -> 6 | G67: 42619 | H67: =(DATEDIF(B67,G67,"D")) -> 10 | I67: H | J67: IRL | K67: =VLOOKUP(J67,countries,2,false) -> Ireland | L67: =VLOOKUP($J67,countries,5,false) -> Europe | M67: =VLOOKUP($J67,countries,6,false) -> Northern Europe | N67: 8293 | O67: =VLOOKUP(N67, products, 2, FALSE) -> Cosmetics | P67: Offline | Q67: 1625 | R67: 437.2 | S67: 263.33 | U67: =Q67*R67 -> 710450 | V67: =Q67*S67 -> 427911.25 | W67: =U67-V67 -> 282538.75
A68: 139949357 | B68: 41821 | C68: =YEAR(B68) -> 2014 | D68: =TEXT(B68,"MM - MMM") -> 07 - Jul | E68: =CHOOSE(WEEKDAY(B68,2),"Mon","Tue","Wed","Thu","Fri","Sat","Sun") -> Tue | F68: =MATCH(E68,{"Mon","Tue","Wed","Thu","Fri","Sat","Sun"}, 0) -> 2 | G68: 41834 | H68: =(DATEDIF(B68,G68,"D")) -> 13 | I68: H | J68: Unknown | K68: Unknown | L68: Unknown | M68: Unknown | N68: 5988 | O68: =VLOOKUP(N68, products, 2, FALSE) -> Vegetables | P68: Online | Q68: 2980 | R68: 154.06 | S68: 90.93 | U68: =Q68*R68 -> 459098.8 | V68: =Q68*S68 -> 270971.4 | W68: =U68-V68 -> 188127.4
A69: 140461766 | B69: 41828 | C69: =YEAR(B69) -> 2014 | D69: =TEXT(B69,"MM - MMM") -> 07 - Jul | E69: =CHOOSE(WEEKDAY(B69,2),"Mon","Tue","Wed","Thu","Fri","Sat","Sun") -> Tue | F69: =MATCH(E69,{"Mon","Tue","Wed","Thu","Fri","Sat","Sun"}, 0) -> 2 | G69: 41840 | H69: =(DATEDIF(B69,G69,"D")) -> 12 | I69: C | J69: UKR | K69: =VLOOKUP(J69,countries,2,false) -> Ukraine | L69: =VLOOKUP($J69,countries,5,false) -> Europe | M69: =VLOOKUP($J69,countries,6,false) -> Eastern Europe | N69: 8293 | O69: =VLOOKUP(N69, products, 2, FALSE) -> Cosmetics | P69: Online | Q69: 4613 | R69: 437.2 | S69: 263.33 | U69: =Q69*R69 -> 2016803.6 | V69: =Q69*S69 -> 1214741.3 | W69: =U69-V69 -> 802062.31
A70: 140499961 | B70: 40631 | C70: =YEAR(B70) -> 2011 | D70: =TEXT(B70,"MM - MMM") -> 03 - Mar | E70: =CHOOSE(WEEKDAY(B70,2),"Mon","Tue","Wed","Thu","Fri","Sat","Sun") -> Tue | F70: =MATCH(E70,{"Mon","Tue","Wed","Thu","Fri","Sat","Sun"}, 0) -> 2 | G70: 40663 | H70: =(DATEDIF(B70,G70,"D")) -> 32 | I70: L | J70: LVA | K70: =VLOOKUP(J70,countries,2,false) -> Latvia | L70: =VLOOKUP($J70,countries,5,false) -> Europe | M70: =VLOOKUP($J70,countries,6,false) -> Northern Europe | N70: 3127 | O70: =VLOOKUP(N70, products, 2, FALSE) -> Personal Care | P70: Online | Q70: 5915 | R70: 81.73 | S70: 56.67 | U70: =Q70*R70 -> 483432.95 | V70: =Q70*S70 -> 335203.05 | W70: =U70-V70 -> 148229.9
A71: 141764247 | B71: 41470 | C71: =YEAR(B71) -> 2013 | D71: =TEXT(B71,"MM - MMM") -> 07 - Jul | E71: =CHOOSE(WEEKDAY(B71,2),"Mon","Tue","Wed","Thu","Fri","Sat","Sun") -> Mon | F71: =MATCH(E71,{"Mon","Tue","Wed","Thu","Fri","Sat","Sun"}, 0) -> 1 | G71: 41515 | H71: =(DATEDIF(B71,G71,"D")) -> 45 | I71: H | J71: AND | K71: =VLOOKUP(J71,countries,2,false) -> Andorra | L71: =VLOOKUP($J71,countries,5,false) -> Europe | M71: =VLOOKUP($J71,countries,6,false) -> Southern Europe | N71: 7331 | O71: =VLOOKUP(N71, products, 2, FALSE) -> Baby Food | P71: Offline | Q71: 46 | R71: 255.28 | S71: 159.42 | U71: =Q71*R71 -> 11742.88 | V71: =Q71*S71 -> 7333.32 | W71: =U71-V71 -> 4409.56
A72: 141846215 | B72: 41108 | C72: =YEAR(B72) -> 2012 | D72: =TEXT(B72,"MM - MMM") -> 07 - Jul | E72: =CHOOSE(WEEKDAY(B72,2),"Mon","Tue","Wed","Thu","Fri","Sat","Sun") -> Wed | F72: =MATCH(E72,{"Mon","Tue","Wed","Thu","Fri","Sat","Sun"}, 0) -> 3 | G72: 41137 | H72: =(DATEDIF(B72,G72,"D")) -> 29 | I72: H | J72: GEO | K72: =VLOOKUP(J72,countries,2,false) -> Georgia | L72: =VLOOKUP($J72,countries,5,false) -> Asia | M72: =VLOOKUP($J72,countries,6,false) -> Western Asia | N72: 2455 | O72: =VLOOKUP(N72, products, 2, FALSE) -> Clothes | P72: Online | Q72: 4302 | R72: 109.28 | S72: 35.84 | U72: =Q72*R72 -> 470122.56 | V72: =Q72*S72 -> 154183.68 | W72: =U72-V72 -> 315938.88
A73: 141875827 | B73: 40615 | C73: =YEAR(B73) -> 2011 | D73: =TEXT(B73,"MM - MMM") -> 03 - Mar | E73: =CHOOSE(WEEKDAY(B73,2),"Mon","Tue","Wed","Thu","Fri","Sat","Sun") -> Sun | F73: =MATCH(E73,{"Mon","Tue","Wed","Thu","Fri","Sat","Sun"}, 0) -> 7 | G73: 40649 | H73: =(DATEDIF(B73,G73,"D")) -> 34 | I73: C | J73: POL | K73: =VLOOKUP(J73,countries,2,false) -> Poland | L73: =VLOOKUP($J73,countries,5,false) -> Europe | M73: =VLOOKUP($J73,countries,6,false) -> Eastern Europe | N73: 7940 | O73: =VLOOKUP(N73, products, 2, FALSE) -> Household | P73: Online | Q73: 3065 | R73: 668.27 | S73: 502.54 | U73: =Q73*R73 -> 2048247.6 | V73: =Q73*S73 -> 1540285.1 | W73: =U73-V73 -> 507962.45
A74: 142375361 | B74: 41678 | C74: =YEAR(B74) -> 2014 | D74: =TEXT(B74,"MM - MMM") -> 02 - Feb | E74: =CHOOSE(WEEKDAY(B74,2),"Mon","Tue","Wed","Thu","Fri","Sat","Sun") -> Sat | F74: =MATCH(E74,{"Mon","Tue","Wed","Thu","Fri","Sat","Sun"}, 0) -> 6 | G74: 41689 | H74: =(DATEDIF(B74,G74,"D")) -> 11 | I74: L | J74: LIE | K74: =VLOOKUP(J74,countries,2,false) -> Liechtenstein | L74: =VLOOKUP($J74,countries,5,false) -> Europe | M74: =VLOOKUP($J74,countries,6,false) -> Western Europe | N74: 4594 | O74: =VLOOKUP(N74, products, 2, FALSE) -> Fruits | P74: Online | Q74: 888 | R74: 9.33 | S74: 6.92 | U74: =Q74*R74 -> 8285.04 | V74: =Q74*S74 -> 6144.96 | W74: =U74-V74 -> 2140.08
A75: 142987763 | B75: 41504 | C75: =YEAR(B75) -> 2013 | D75: =TEXT(B75,"MM - MMM") -> 08 - Aug | E75: =CHOOSE(WEEKDAY(B75,2),"Mon","Tue","Wed","Thu","Fri","Sat","Sun") -> Sun | F75: =MATCH(E75,{"Mon","Tue","Wed","Thu","Fri","Sat","Sun"}, 0) -> 7 | G75: 41518 | H75: =(DATEDIF(B75,G75,"D")) -> 14 | I75: L | J75: NLD | K75: =VLOOKUP(J75,countries,2,false) -> Netherlands | L75: =VLOOKUP($J75,countries,5,false) -> Europe | M75: =VLOOKUP($J75,countries,6,false) -> Western Europe | N75: 7940 | O75: =VLOOKUP(N75, products, 2, FALSE) -> Household | P75: Offline | Q75: 2112 | R75: 668.27 | S75: 502.54 | U75: =Q75*R75 -> 1411386.2 | V75: =Q75*S75 -> 1061364.5 | W75: =U75-V75 -> 350021.76
A76: 143414771 | B76: 41050 | C76: =YEAR(B76) -> 2012 | D76: =TEXT(B76,"MM - MMM") -> 05 - May | E76: =CHOOSE(WEEKDAY(B76,2),"Mon","Tue","Wed","Thu","Fri","Sat","Sun") -> Mon | F76: =MATCH(E76,{"Mon","Tue","Wed","Thu","Fri","Sat","Sun"}, 0) -> 1 | G76: 41063 | H76: =(DATEDIF(B76,G76,"D")) -> 13 | I76: H | J76: IRL | K76: =VLOOKUP(J76,countries,2,false) -> Ireland | L76: =VLOOKUP($J76,countries,5,false) -> Europe | M76: =VLOOKUP($J76,countries,6,false) -> Northern Europe | N76: 7940 | O76: =VLOOKUP(N76, products, 2, FALSE) -> Household | P76: Offline | Q76: 8473 | R76: 668.27 | S76: 502.54 | U76: =Q76*R76 -> 5662251.7 | V76: =Q76*S76 -> 4258021.4 | W76: =U76-V76 -> 1404230.3
A77: 144282948 | B77: 41468 | C77: =YEAR(B77) -> 2013 | D77: =TEXT(B77,"MM - MMM") -> 07 - Jul | E77: =CHOOSE(WEEKDAY(B77,2),"Mon","Tue","Wed","Thu","Fri","Sat","Sun") -> Sat | F77: =MATCH(E77,{"Mon","Tue","Wed","Thu","Fri","Sat","Sun"}, 0) -> 6 | G77: 41487 | H77: =(DATEDIF(B77,G77,"D")) -> 19 | I77: H | J77: FIN | K77: =VLOOKUP(J77,countries,2,false) -> Finland | L77: =VLOOKUP($J77,countries,5,false) -> Europe | M77: =VLOOKUP($J77,countries,6,false) -> Northern Europe | N77: 2103 | O77: =VLOOKUP(N77, products, 2, FALSE) -> Cereal | P77: Online | Q77: 5386 | R77: 205.7 | S77: 117.11 | U77: =Q77*R77 -> 1107900.2 | V77: =Q77*S77 -> 630754.46 | W77: =U77-V77 -> 477145.74
A78: 144743001 | B78: 41345 | C78: =YEAR(B78) -> 2013 | D78: =TEXT(B78,"MM - MMM") -> 03 - Mar | E78: =CHOOSE(WEEKDAY(B78,2),"Mon","Tue","Wed","Thu","Fri","Sat","Sun") -> Tue | F78: =MATCH(E78,{"Mon","Tue","Wed","Thu","Fri","Sat","Sun"}, 0) -> 2 | G78: 41385 | H78: =(DATEDIF(B78,G78,"D")) -> 40 | I78: M | J78: SVN | K78: =VLOOKUP(J78,countries,2,false) -> Slovenia | L78: =VLOOKUP($J78,countries,5,false) -> Europe | M78: =VLOOKUP($J78,countries,6,false) -> Southern Europe | N78: 7331 | O78: =VLOOKUP(N78, products, 2, FALSE) -> Baby Food | P78: Offline | Q78: 1525 | R78: 255.28 | S78: 159.42 | U78: =Q78*R78 -> 389302 | V78: =Q78*S78 -> 243115.5 | W78: =U78-V78 -> 146186.5
A79: 144978606 | B79: 40549 | C79: =YEAR(B79) -> 2011 | D79: =TEXT(B79,"MM - MMM") -> 01 - Jan | E79: =CHOOSE(WEEKDAY(B79,2),"Mon","Tue","Wed","Thu","Fri","Sat","Sun") -> Thu | F79: =MATCH(E79,{"Mon","Tue","Wed","Thu","Fri","Sat","Sun"}, 0) -> 4 | G79: 40593 | H79: =(DATEDIF(B79,G79,"D")) -> 44 | I79: C | J79: IRL | K79: =VLOOKUP(J79,countries,2,false) -> Ireland | L79: =VLOOKUP($J79,countries,5,false) -> Europe | M79: =VLOOKUP($J79,countries,6,false) -> Northern Europe | N79: 8681 | O79: =VLOOKUP(N79, products, 2, FALSE) -> Office Supplies | P79: Online | Q79: 1246 | R79: 651.21 | S79: 524.96 | U79: =Q79*R79 -> 811407.66 | V79: =Q79*S79 -> 654100.16 | W79: =U79-V79 -> 157307.5
A80: 146349751 | B80: 42856 | C80: =YEAR(B80) -> 2017 | D80: =TEXT(B80,"MM - MMM") -> 05 - May | E80: =CHOOSE(WEEKDAY(B80,2),"Mon","Tue","Wed","Thu","Fri","Sat","Sun") -> Mon | F80: =MATCH(E80,{"Mon","Tue","Wed","Thu","Fri","Sat","Sun"}, 0) -> 1 | G80: 42899 | H80: =(DATEDIF(B80,G80,"D")) -> 43 | I80: M | J80: LTU | K80: =VLOOKUP(J80,countries,2,false) -> Lithuania | L80: =VLOOKUP($J80,countries,5,false) -> Europe | M80: =VLOOKUP($J80,countries,6,false) -> Northern Europe | N80: 5988 | O80: =VLOOKUP(N80, products, 2, FALSE) -> Vegetables | P80: Online | Q80: 6999 | R80: 154.06 | S80: 90.93 | U80: =Q80*R80 -> 1078265.9 | V80: =Q80*S80 -> 636419.07 | W80: =U80-V80 -> 441846.87
... A84: 149274003 | B84: 41393 | C84: =YEAR(B84) -> 2013 | D84: =TEXT(B84,"MM - MMM") -> 04 - Apr | E84: =CHOOSE(WEEKDAY(B84,2),"Mon","Tue","Wed","Thu","Fri","Sat","Sun") -> Mon | F84: =MATCH(E84,{"Mon","Tue","Wed","Thu","Fri","Sat","Sun"}, 0) -> 1 | G84: 41423 | H84: =(DATEDIF(B84,G84,"D")) -> 30 | I84: C | J84: NOR | K84: =VLOOKUP(J84,countries,2,false) -> Norway | L84: =VLOOKUP($J84,countries,5,false) -> Europe | M84: =VLOOKUP($J84,countries,6,false) -> Northern Europe | N84: 7940 | O84: =VLOOKUP(N84, products, 2, FALSE) -> Household | P84: Offline | Q84: 2350 | R84: 668.27 | S84: 502.54 | U84: =Q84*R84 -> 1570434.5 | V84: =Q84*S84 -> 1180969 | W84: =U84-V84 -> 389465.5
A85: 150293242 | B85: 42143 | C85: =YEAR(B85) -> 2015 | D85: =TEXT(B85,"MM - MMM") -> 05 - May | E85: =CHOOSE(WEEKDAY(B85,2),"Mon","Tue","Wed","Thu","Fri","Sat","Sun") -> Tue | F85: =MATCH(E85,{"Mon","Tue","Wed","Thu","Fri","Sat","Sun"}, 0) -> 2 | G85: 42176 | H85: =(DATEDIF(B85,G85,"D")) -> 33 | I85: H | J85: Unknown | K85: Unknown | L85: Unknown | M85: Unknown | N85: 8681 | O85: =VLOOKUP(N85, products, 2, FALSE) -> Office Supplies | P85: Offline | Q85: 3965 | R85: 651.21 | S85: 524.96 | U85: =Q85*R85 -> 2582047.6 | V85: =Q85*S85 -> 2081466.4 | W85: =U85-V85 -> 500581.25
A86: 151312482 | B86: 42892 | C86: =YEAR(B86) -> 2017 | D86: =TEXT(B86,"MM - MMM") -> 06 - Jun | E86: =CHOOSE(WEEKDAY(B86,2),"Mon","Tue","Wed","Thu","Fri","Sat","Sun") -> Tue | F86: =MATCH(E86,{"Mon","Tue","Wed","Thu","Fri","Sat","Sun"}, 0) -> 2 | G86: 42928 | H86: =(DATEDIF(B86,G86,"D")) -> 36 | I86: H | J86: CZE | K86: =VLOOKUP(J86,countries,2,false) -> Czech Republic | L86: =VLOOKUP($J86,countries,5,false) -> Europe | M86: =VLOOKUP($J86,countries,6,false) -> Eastern Europe | N86: 8293 | O86: =VLOOKUP(N86, products, 2, FALSE) -> Cosmetics | P86: Online | Q86: 5581 | R86: 437.2 | S86: 263.33 | U86: =Q86*R86 -> 2440013.2 | V86: =Q86*S86 -> 1469644.7 | W86: =U86-V86 -> 970368.47
A87: 152191388 | B87: 41047 | C87: =YEAR(B87) -> 2012 | D87: =TEXT(B87,"MM - MMM") -> 05 - May | E87: =CHOOSE(WEEKDAY(B87,2),"Mon","Tue","Wed","Thu","Fri","Sat","Sun") -> Fri | F87: =MATCH(E87,{"Mon","Tue","Wed","Thu","Fri","Sat","Sun"}, 0) -> 5 | G87: 41082 | H87: =(DATEDIF(B87,G87,"D")) -> 35 | I87: L | J87: ALB | K87: =VLOOKUP(J87,countries,2,false) -> Albania | L87: =VLOOKUP($J87,countries,5,false) -> Europe | M87: =VLOOKUP($J87,countries,6,false) -> Southern Europe | N87: 7331 | O87: =VLOOKUP(N87, products, 2, FALSE) -> Baby Food | P87: Offline | Q87: 5669 | R87: 255.28 | S87: 159.42 | U87: =Q87*R87 -> 1447182.3 | V87: =Q87*S87 -> 903751.98 | W87: =U87-V87 -> 543430.34
A88: 152411115 | B88: 41278 | C88: =YEAR(B88) -> 2013 | D88: =TEXT(B88,"MM - MMM") -> 01 - Jan | E88: =CHOOSE(WEEKDAY(B88,2),"Mon","Tue","Wed","Thu","Fri","Sat","Sun") -> Fri | F88: =MATCH(E88,{"Mon","Tue","Wed","Thu","Fri","Sat","Sun"}, 0) -> 5 | G88: 41326 | H88: =(DATEDIF(B88,G88,"D")) -> 48 | I88: H | J88: SWE | K88: =VLOOKUP(J88,countries,2,false) -> Sweden | L88: =VLOOKUP($J88,countries,5,false) -> Europe | M88: =VLOOKUP($J88,countries,6,false) -> Northern Europe | N88: 8875 | O88: =VLOOKUP(N88, products, 2, FALSE) -> Meat | P88: Online | Q88: 691 | R88: 421.89 | S88: 364.69 | U88: =Q88*R88 -> 291525.99 | V88: =Q88*S88 -> 252000.79 | W88: =U88-V88 -> 39525.2
A89: 152505099 | B89: 41036 | C89: =YEAR(B89) -> 2012 | D89: =TEXT(B89,"MM - MMM") -> 05 - May | E89: =CHOOSE(WEEKDAY(B89,2),"Mon","Tue","Wed","Thu","Fri","Sat","Sun") -> Mon | F89: =MATCH(E89,{"Mon","Tue","Wed","Thu","Fri","Sat","Sun"}, 0) -> 1 | G89: 41048 | H89: =(DATEDIF(B89,G89,"D")) -> 12 | I89: M | J89: SMR | K89: =VLOOKUP(J89,countries,2,false) -> San Marino | L89: =VLOOKUP($J89,countries,5,false) -> Europe | M89: =VLOOKUP($J89,countries,6,false) -> Southern Europe | N89: 2455 | O89: =VLOOKUP(N89, products, 2, FALSE) -> Clothes | P89: Offline | Q89: 8503 | R89: 109.28 | S89: 35.84 | U89: =Q89*R89 -> 929207.84 | V89: =Q89*S89 -> 304747.52 | W89: =U89-V89 -> 624460.32
A90: 152746713 | B90: 40300 | C90: =YEAR(B90) -> 2010 | D90: =TEXT(B90,"MM - MMM") -> 05 - May | E90: =CHOOSE(WEEKDAY(B90,2),"Mon","Tue","Wed","Thu","Fri","Sat","Sun") -> Sun | F90: =MATCH(E90,{"Mon","Tue","Wed","Thu","Fri","Sat","Sun"}, 0) -> 7 | G90: 40306 | H90: =(DATEDIF(B90,G90,"D")) -> 6 | I90: C | J90: BIH | K90: =VLOOKUP(J90,countries,2,false) -> Bosnia and Herzegovina | L90: =VLOOKUP($J90,countries,5,false) -> Europe | M90: =VLOOKUP($J90,countries,6,false) -> Southern Europe | N90: 8681 | O90: =VLOOKUP(N90, products, 2, FALSE) -> Office Supplies | P90: Offline | Q90: 2 | R90: 651.21 | S90: 524.96 | U90: =Q90*R90 -> 1302.42 | V90: =Q90*S90 -> 1049.92 | W90: =U90-V90 -> 252.5
A91: 153974950 | B91: 40777 | C91: =YEAR(B91) -> 2011 | D91: =TEXT(B91,"MM - MMM") -> 08 - Aug | E91: =CHOOSE(WEEKDAY(B91,2),"Mon","Tue","Wed","Thu","Fri","Sat","Sun") -> Mon | F91: =MATCH(E91,{"Mon","Tue","Wed","Thu","Fri","Sat","Sun"}, 0) -> 1 | G91: 40806 | H91: =(DATEDIF(B91,G91,"D")) -> 29 | I91: L | J91: SWE | K91: =VLOOKUP(J91,countries,2,false) -> Sweden | L91: =VLOOKUP($J91,countries,5,false) -> Europe | M91: =VLOOKUP($J91,countries,6,false) -> Northern Europe | N91: 4594 | O91: =VLOOKUP(N91, products, 2, FALSE) -> Fruits | P91: Offline | Q91: 3464 | R91: 9.33 | S91: 6.92 | U91: =Q91*R91 -> 32319.12 | V91: =Q91*S91 -> 23970.88 | W91: =U91-V91 -> 8348.24
A92: 155086886 | B92: 41667 | C92: =YEAR(B92) -> 2014 | D92: =TEXT(B92,"MM - MMM") -> 01 - Jan | E92: =CHOOSE(WEEKDAY(B92,2),"Mon","Tue","Wed","Thu","Fri","Sat","Sun") -> Tue | F92: =MATCH(E92,{"Mon","Tue","Wed","Thu","Fri","Sat","Sun"}, 0) -> 2 | G92: 41675 | H92: =(DATEDIF(B92,G92,"D")) -> 8 | I92: M | J92: SVN | K92: =VLOOKUP(J92,countries,2,false) -> Slovenia | L92: =VLOOKUP($J92,countries,5,false) -> Europe | M92: =VLOOKUP($J92,countries,6,false) -> Southern Europe | N92: 8293 | O92: =VLOOKUP(N92, products, 2, FALSE) -> Cosmetics | P92: Offline | Q92: 2511 | R92: 437.2 | S92: 263.33 | U92: =Q92*R92 -> 1097809.2 | V92: =Q92*S92 -> 661221.63 | W92: =U92-V92 -> 436587.57
A93: 155914723 | B93: 42075 | C93: =YEAR(B93) -> 2015 | D93: =TEXT(B93,"MM - MMM") -> 03 - Mar | E93: =CHOOSE(WEEKDAY(B93,2),"Mon","Tue","Wed","Thu","Fri","Sat","Sun") -> Thu | F93: =MATCH(E93,{"Mon","Tue","Wed","Thu","Fri","Sat","Sun"}, 0) -> 4 | G93: 42092 | H93: =(DATEDIF(B93,G93,"D")) -> 17 | I93: H | J93: IRL | K93: =VLOOKUP(J93,countries,2,false) -> Ireland | L93: =VLOOKUP($J93,countries,5,false) -> Europe | M93: =VLOOKUP($J93,countries,6,false) -> Northern Europe | N93: 4594 | O93: =VLOOKUP(N93, products, 2, FALSE) -> Fruits | P93: Offline | Q93: 7486 | R93: 9.33 | S93: 6.92 | U93: =Q93*R93 -> 69844.38 | V93: =Q93*S93 -> 51803.12 | W93: =U93-V93 -> 18041.26
A94: 156158483 | B94: 42547 | C94: =YEAR(B94) -> 2016 | D94: =TEXT(B94,"MM - MMM") -> 06 - Jun | E94: =CHOOSE(WEEKDAY(B94,2),"Mon","Tue","Wed","Thu","Fri","Sat","Sun") -> Sun | F94: =MATCH(E94,{"Mon","Tue","Wed","Thu","Fri","Sat","Sun"}, 0) -> 7 | G94: 42587 | H94: =(DATEDIF(B94,G94,"D")) -> 40 | I94: C | J94: LTU | K94: =VLOOKUP(J94,countries,2,false) -> Lithuania | L94: =VLOOKUP($J94,countries,5,false) -> Europe | M94: =VLOOKUP($J94,countries,6,false) -> Northern Europe | N94: 2455 | O94: =VLOOKUP(N94, products, 2, FALSE) -> Clothes | P94: Offline | Q94: 9620 | R94: 109.28 | S94: 35.84 | U94: =Q94*R94 -> 1051273.6 | V94: =Q94*S94 -> 344780.8 | W94: =U94-V94 -> 706492.8
A95: 158479773 | B95: 42143 | C95: =YEAR(B95) -> 2015 | D95: =TEXT(B95,"MM - MMM") -> 05 - May | E95: =CHOOSE(WEEKDAY(B95,2),"Mon","Tue","Wed","Thu","Fri","Sat","Sun") -> Tue | F95: =MATCH(E95,{"Mon","Tue","Wed","Thu","Fri","Sat","Sun"}, 0) -> 2 | G95: 42173 | H95: =(DATEDIF(B95,G95,"D")) -> 30 | I95: L | J95: RUS | K95: =VLOOKUP(J95,countries,2,false) -> Russia | L95: =VLOOKUP($J95,countries,5,false) -> Europe | M95: =VLOOKUP($J95,countries,6,false) -> Eastern Europe | N95: 7331 | O95: =VLOOKUP(N95, products, 2, FALSE) -> Baby Food | P95: Offline | Q95: 6542 | R95: 255.28 | S95: 159.42 | U95: =Q95*R95 -> 1670041.8 | V95: =Q95*S95 -> 1042925.6 | W95: =U95-V95 -> 627116.12
A96: 158673751 | B96: 41720 | C96: =YEAR(B96) -> 2014 | D96: =TEXT(B96,"MM - MMM") -> 03 - Mar | E96: =CHOOSE(WEEKDAY(B96,2),"Mon","Tue","Wed","Thu","Fri","Sat","Sun") -> Sat | F96: =MATCH(E96,{"Mon","Tue","Wed","Thu","Fri","Sat","Sun"}, 0) -> 6 | G96: 41769 | H96: =(DATEDIF(B96,G96,"D")) -> 49 | I96: H | J96: DEU | K96: =VLOOKUP(J96,countries,2,false) -> Germany | L96: =VLOOKUP($J96,countries,5,false) -> Europe | M96: =VLOOKUP($J96,countries,6,false) -> Western Europe | N96: 8969 | O96: =VLOOKUP(N96, products, 2, FALSE) -> Snacks | P96: Online | Q96: 3944 | R96: 152.58 | S96: 97.44 | U96: =Q96*R96 -> 601775.52 | V96: =Q96*S96 -> 384303.36 | W96: =U96-V96 -> 217472.16
A97: 159232509 | B97: 41798 | C97: =YEAR(B97) -> 2014 | D97: =TEXT(B97,"MM - MMM") -> 06 - Jun | E97: =CHOOSE(WEEKDAY(B97,2),"Mon","Tue","Wed","Thu","Fri","Sat","Sun") -> Sun | F97: =MATCH(E97,{"Mon","Tue","Wed","Thu","Fri","Sat","Sun"}, 0) -> 7 | G97: 41834 | H97: =(DATEDIF(B97,G97,"D")) -> 36 | I97: H | J97: CHE | K97: =VLOOKUP(J97,countries,2,false) -> Switzerland | L97: =VLOOKUP($J97,countries,5,false) -> Europe | M97: =VLOOKUP($J97,countries,6,false) -> Western Europe | N97: 4594 | O97: =VLOOKUP(N97, products, 2, FALSE) -> Fruits | P97: Online | Q97: 9293 | R97: 9.33 | S97: 6.92 | U97: =Q97*R97 -> 86703.69 | V97: =Q97*S97 -> 64307.56 | W97: =U97-V97 -> 22396.13
A98: 159805858 | B98: 41232 | C98: =YEAR(B98) -> 2012 | D98: =TEXT(B98,"MM - MMM") -> 11 - Nov | E98: =CHOOSE(WEEKDAY(B98,2),"Mon","Tue","Wed","Thu","Fri","Sat","Sun") -> Mon | F98: =MATCH(E98,{"Mon","Tue","Wed","Thu","Fri","Sat","Sun"}, 0) -> 1 | G98: 41260 | H98: =(DATEDIF(B98,G98,"D")) -> 28 | I98: M | J98: Unknown | K98: Unknown | L98: Unknown | M98: Unknown | N98: 8875 | O98: =VLOOKUP(N98, products, 2, FALSE) -> Meat | P98: Offline | Q98: 8959 | R98: 421.89 | S98: 364.69 | U98: =Q98*R98 -> 3779712.5 | V98: =Q98*S98 -> 3267257.7 | W98: =U98-V98 -> 512454.8
A99: 160578763 | B99: 42274 | C99: =YEAR(B99) -> 2015 | D99: =TEXT(B99,"MM - MMM") -> 09 - Sep | E99: =CHOOSE(WEEKDAY(B99,2),"Mon","Tue","Wed","Thu","Fri","Sat","Sun") -> Sun | F99: =MATCH(E99,{"Mon","Tue","Wed","Thu","Fri","Sat","Sun"}, 0) -> 7 | G99: 42307 | H99: =(DATEDIF(B99,G99,"D")) -> 33 | I99: L | J99: ROU | K99: =VLOOKUP(J99,countries,2,false) -> Romania | L99: =VLOOKUP($J99,countries,5,false) -> Europe | M99: =VLOOKUP($J99,countries,6,false) -> Eastern Europe | N99: 8681 | O99: =VLOOKUP(N99, products, 2, FALSE) -> Office Supplies | P99: Online | Q99: 7679 | R99: 651.21 | S99: 524.96 | U99: =Q99*R99 -> 5000641.6 | V99: =Q99*S99 -> 4031167.8 | W99: =U99-V99 -> 969473.75
A100: 160751283 | B100: 40845 | C100: =YEAR(B100) -> 2011 | D100: =TEXT(B100,"MM - MMM") -> 10 - Oct | E100: =CHOOSE(WEEKDAY(B100,2),"Mon","Tue","Wed","Thu","Fri","Sat","Sun") -> Sat | F100: =MATCH(E100,{"Mon","Tue","Wed","Thu","Fri","Sat","Sun"}, 0) -> 6 | G100: 40860 | H100: =(DATEDIF(B100,G100,"D")) -> 15 | I100: C | J100: LVA | K100: =VLOOKUP(J100,countries,2,false) -> Latvia | L100: =VLOOKUP($J100,countries,5,false) -> Europe | M100: =VLOOKUP($J100,countries,6,false) -> Northern Europe | N100: 3127 | O100: =VLOOKUP(N100, products, 2, FALSE) -> Personal Care | P100: Offline | Q100: 8732 | R100: 81.73 | S100: 56.67 | U100: =Q100*R100 -> 713666.36 | V100: =Q100*S100 -> 494842.44 | W100: =U100-V100 -> 218823.92
A101: 161399304 | B101: 40238 | C101: =YEAR(B101) -> 2010 | D101: =TEXT(B101,"MM - MMM") -> 03 - Mar | E101: =CHOOSE(WEEKDAY(B101,2),"Mon","Tue","Wed","Thu","Fri","Sat","Sun") -> Mon | F101: =MATCH(E101,{"Mon","Tue","Wed","Thu","Fri","Sat","Sun"}, 0) -> 1 | G101: 40252 | H101: =(DATEDIF(B101,G101,"D")) -> 14 | I101: L | J101: SVK | K101: =VLOOKUP(J101,countries,2,false) -> Slovakia | L101: =VLOOKUP($J101,countries,5,false) -> Europe | M101: =VLOOKUP($J101,countries,6,false) -> Eastern Europe | N101: 8293 | O101: =VLOOKUP(N101, products, 2, FALSE) -> Cosmetics | P101: online | Q101: 496 | R101: 437.2 | S101: 263.33 | U101: =Q101*R101 -> 216851.2 | V101: =Q101*S101 -> 130611.68 | W101: =U101-V101 -> 86239.52
A102: 161607444 | B102: 41143 | C102: =YEAR(B102) -> 2012 | D102: =TEXT(B102,"MM - MMM") -> 08 - Aug | E102: =CHOOSE(WEEKDAY(B102,2),"Mon","Tue","Wed","Thu","Fri","Sat","Sun") -> Wed | F102: =MATCH(E102,{"Mon","Tue","Wed","Thu","Fri","Sat","Sun"}, 0) -> 3 | G102: 41185 | H102: =(DATEDIF(B102,G102,"D")) -> 42 | I102: L | J102: ROU | K102: =VLOOKUP(J102,countries,2,false) -> Romania | L102: =VLOOKUP($J102,countries,5,false) -> Europe | M102: =VLOOKUP($J102,countries,6,false) -> Eastern Europe | N102: 8875 | O102: =VLOOKUP(N102, products, 2, FALSE) -> Meat | P102: Offline | Q102: 2089 | R102: 421.89 | S102: 364.69 | U102: =Q102*R102 -> 881328.21 | V102: =Q102*S102 -> 761837.41 | W102: =U102-V102 -> 119490.8
A103: 161812150 | B103: 41222 | C103: =YEAR(B103) -> 2012 | D103: =TEXT(B103,"MM - MMM") -> 11 - Nov | E103: =CHOOSE(WEEKDAY(B103,2),"Mon","Tue","Wed","Thu","Fri","Sat","Sun") -> Fri | F103: =MATCH(E103,{"Mon","Tue","Wed","Thu","Fri","Sat","Sun"}, 0) -> 5 | G103: 41225 | H103: =(DATEDIF(B103,G103,"D")) -> 3 | I103: C | J103: DNK | K103: =VLOOKUP(J103,countries,2,false) -> Denmark | L103: =VLOOKUP($J103,countries,5,false) -> Europe | M103: =VLOOKUP($J103,countries,6,false) -> Northern Europe | N103: 2455 | O103: =VLOOKUP(N103, products, 2, FALSE) -> Clothes | P103: Online | Q103: 2666 | R103: 109.28 | S103: 35.84 | U103: =Q103*R103 -> 291340.48 | V103: =Q103*S103 -> 95549.44 | W103: =U103-V103 -> 195791.04
...

Sheet products
A1: id | B1: item_type
A2: 2103 | B2: Cereal
A3: 7940 | B3: Household
A4: 2455 | B4: Clothes
A5: 1270 | B5: Beverages
A6: 8681 | B6: Office Supplies
A7: 4594 | B7: Fruits
A8: 5988 | B8: Vegetables
A9: 7331 | B9: Baby Food
A10: 8875 | B10: Meat
A11: 8293 | B11: Cosmetics
A12: 8969 | B12: Snacks
A13: 3127 | B13: Personal Care

Sheet 4.Metrics
A1: Total number of orders | B1: =COUNTA(events!A2:A1000) -> 1330
A2: Total profit | B2: =SUM(events!W2:W1000) -> 501434459
A3: Total number of contries | B3: =IFERROR(__xludf.DUMMYFUNCTION("COUNTUNIQUE(events!J2:J1000)"),46.0) -> 46
A4: Total revenue | B4: =SUM(events!U2:U1000) -> 1702129408

Sheet 5.Analysis of products
A1: id | B1: item_type | C1: Orders count | E1: id | F1: item_type | G1: revenue | I1: id | J1: item_type | K1: cost | M1: id | N1: item_type | O1: profit
A2: 8681 | B2: Office Supplies | C2: =COUNTIF(product_id, A2) -> 123 | E2: 8681 | F2: Office Supplies | G2: =SUMIF(product_id, E2, total_revenue) -> 4.02214e+08 | I2: 8681 | J2: Office Supplies | K2: =SUMIF(product_id,I2, total_cost) -> 3.2423682e+08 | M2: 8293 | N2: Cosmetics | O2: =SUMIF(product_id, M2, total_profit) -> 92723306
A3: 1270 | B3: Beverages | C3: =COUNTIF(product_id, A3) -> 121 | E3: 7940 | F3: Household | G3: =SUMIF(product_id, E3, total_revenue) -> 2.942052e+08 | I3: 7940 | J3: Household | K3: =SUMIF(product_id,I3, total_cost) -> 2.2124273e+08 | M3: 8681 | N3: Office Supplies | O3: =SUMIF(product_id, M3, total_profit) -> 77977176
A4: 3127 | B4: Personal Care | C4: =COUNTIF(product_id, A4) -> 115 | E4: 8293 | F4: Cosmetics | G4: =SUMIF(product_id, E4, total_revenue) -> 2.3315483e+08 | I4: 8875 | J4: Meat | K4: =SUMIF(product_id,I4, total_cost) -> 1.9342428e+08 | M4: 7940 | N4: Household | O4: =SUMIF(product_id, M4, total_profit) -> 72962467
A5: 8293 | B5: Cosmetics | C5: =COUNTIF(product_id, A5) -> 114 | E5: 8875 | F5: Meat | G5: =SUMIF(product_id, E5, total_revenue) -> 2.2376202e+08 | I5: 8293 | J5: Cosmetics | K5: =SUMIF(product_id,I5, total_cost) -> 140431519 | M5: 7331 | N5: Baby Food | O5: =SUMIF(product_id, M5, total_profit) -> 53940997
A6: 5988 | B6: Vegetables | C6: =COUNTIF(product_id, A6) -> 114 | E6: 7331 | F6: Baby Food | G6: =SUMIF(product_id, E6, total_revenue) -> 1.4364759e+08 | I6: 7331 | J6: Baby Food | K6: =SUMIF(product_id,I6, total_cost) -> 89706591 | M6: 2455 | N6: Clothes | O6: =SUMIF(product_id, M6, total_profit) -> 43431314
A7: 7331 | B7: Baby Food | C7: =COUNTIF(product_id, A7) -> 112 | E7: 2103 | F7: Cereal | G7: =SUMIF(product_id, E7, total_revenue) -> 95791404 | I7: 2103 | J7: Cereal | K7: =SUMIF(product_id,I7, total_cost) -> 54536370 | M7: 2103 | N7: Cereal | O7: =SUMIF(product_id, M7, total_profit) -> 41255034
A8: 4594 | B8: Fruits | C8: =COUNTIF(product_id, A8) -> 112 | E8: 5988 | F8: Vegetables | G8: =SUMIF(product_id, E8, total_revenue) -> 89746729 | I8: 5988 | J8: Vegetables | K8: =SUMIF(product_id,I8, total_cost) -> 52970726 | M8: 5988 | N8: Vegetables | O8: =SUMIF(product_id, M8, total_profit) -> 36776003
A9: 8875 | B9: Meat | C9: =COUNTIF(product_id, A9) -> 111 | E9: 8969 | F9: Snacks | G9: =SUMIF(product_id, E9, total_revenue) -> 74788613 | I9: 8969 | J9: Snacks | K9: =SUMIF(product_id,I9, total_cost) -> 47761190 | M9: 8875 | N9: Meat | O9: =SUMIF(product_id, M9, total_profit) -> 30337736
A10: 2455 | B10: Clothes | C10: =COUNTIF(product_id, A10) -> 105 | E10: 2455 | F10: Clothes | G10: =SUMIF(product_id, E10, total_revenue) -> 64626553 | I10: 3127 | J10: Personal Care | K10: =SUMIF(product_id,I10, total_cost) -> 31603612 | M10: 8969 | N10: Snacks | O10: =SUMIF(product_id, M10, total_profit) -> 27027422
A11: 2103 | B11: Cereal | C11: =COUNTIF(product_id, A11) -> 103 | E11: 3127 | F11: Personal Care | G11: =SUMIF(product_id, E11, total_revenue) -> 45579023 | I11: 2455 | J11: Clothes | K11: =SUMIF(product_id,I11, total_cost) -> 21195238 | M11: 3127 | N11: Personal Care | O11: =SUMIF(product_id, M11, total_profit) -> 13975411
A12: 8969 | B12: Snacks | C12: =COUNTIF(product_id, A12) -> 103 | E12: 1270 | F12: Beverages | G12: =SUMIF(product_id, E12, total_revenue) -> 29093161 | I12: 1270 | J12: Beverages | K12: =SUMIF(product_id,I12, total_cost) -> 19491498 | M12: 1270 | N12: Beverages | O12: =SUMIF(product_id, M12, total_profit) -> 9601662.8
A13: 7940 | B13: Household | C13: =COUNTIF(product_id, A13) -> 97 | E13: 4594 | F13: Fruits | G13: =SUMIF(product_id, E13, total_revenue) -> 5520299.8 | I13: 4594 | J13: Fruits | K13: =SUMIF(product_id,I13, total_cost) -> 4094370.2 | M13: 4594 | N13: Fruits | O13: =SUMIF(product_id, M13, total_profit) -> 1425929.5

Sheet 6.1 Geo_Countries
F3: Revenue by Coutries
F24: Profit by Coutries
F46: Average Shipping Days

Sheet 6.2 Geo_Regions

Sheet 6.3 Geo_Subregions

Sheet 7.Sales channel

Sheet 8.Shipping Duration
A1: Category | B1: Median of Shipping Duration | C1: Orders count | D1: Total profit | G1: region | H1: Countries | I1: Median of Shipping Duration | J1: Orders count | K1: Total profit
A2: Cereal | B2: 29 | C2: 103 | D2: 41255034 | G2: Asia | H2: Georgia | I2: 32 | J2: 23 | K2: 5697679.2
A3: Baby Food | B3: 28.5 | C3: 112 | D3: 53940997 | H3: Armenia | I3: 24 | J3: 29 | K3: 9422353.2
A4: Cosmetics | B4: 28 | C4: 114 | D4: 92723306 | H4: Cyprus | I4: 23.5 | J4: 30 | K4: 10032221
A5: Office Supplies | B5: 27 | C5: 123 | D5: 77977176 | G5: Europe | H5: Hungary | I5: 36 | J5: 25 | K5: 13786231
A6: Snacks | B6: 25 | C6: 103 | D6: 27027422 | H6: Russia | I6: 34 | J6: 32 | K6: 13267683
A7: Meat | B7: 25 | C7: 111 | D7: 30337736 | H7: Monaco | I7: 33 | J7: 13 | K7: 4797048.8
A8: Household | B8: 24 | C8: 97 | D8: 72962467 | H8: Slovakia | I8: 32 | J8: 30 | K8: 12052790
A9: Fruits | B9: 23 | C9: 112 | D9: 1425929.5 | H9: Finland | I9: 31 | J9: 23 | K9: 7525362.8
A10: Beverages | B10: 23 | C10: 121 | D10: 9601662.8 | H10: Luxembourg | I10: 30.5 | J10: 28 | K10: 9870766.1
A11: Vegetables | B11: 21 | C11: 114 | D11: 36776003 | H11: Lithuania | I11: 30 | J11: 25 | K11: 7997297.8
A12: Clothes | B12: 21 | C12: 105 | D12: 43431314 | H12: Bosnia and Herzegovina | I12: 30 | J12: 33 | K12: 13257603
A13: Personal Care | B13: 20 | C13: 115 | D13: 13975411 | H13: Ukraine | I13: 29 | J13: 33 | K13: 14804926
H14: Montenegro | I14: 29 | J14: 28 | K14: 11169661
H15: Austria | I15: 29 | J15: 28 | K15: 10027510
H16: Belgium | I16: 28.5 | J16: 26 | K16: 7476060.1
H17: Sweden | I17: 28 | J17: 29 | K17: 11155329
H18: Czech Republic | I18: 28 | J18: 31 | K18: 13635594
H19: Switzerland | I19: 27.5 | J19: 28 | K19: 11037298
H20: Poland | I20: 27 | J20: 28 | K20: 10671101
H21: Netherlands | I21: 27 | J21: 24 | K21: 5762490.7
H22: Albania | I22: 27 | J22: 21 | K22: 10490706
H23: Belarus | I23: 26.5 | J23: 28 | K23: 11852421
H24: Bulgaria | I24: 26 | J24: 30 | K24: 10408343
H25: Andorra | I25: 26 | J25: 40 | K25: 15410037
... H46: Croatia | I46: 12.5 | J46: 18 | K46: 7318229.4
A53: Does profit depend on the shipping duration?
A54: There is no strong relationship between shipping duration and profit.
A55: Categories with both high and low shipping duration demonstrate a wide range of profitability,
A56: indicating that delivery time is not a key driver of profit.

Sheet 9.1 Sales Dynamics by Year, Mon
P20: Conclusion
P22: Sales fluctuate over time across product categories. There is no consistent yearly growth,
P23: but noticeable monthly seasonality with peaks in mid-year (months 5–7) and declines in months such as 4 and 8.

Sheet 9.2 Sales Dynamics by Year, Mon
E116: Conclusion | P116: Conclusion
E117: Europe generates the majority of profit with clear monthly fluctuations, | P117: Europe consistently generates much higher profit than Asia.
E118: while Asia shows stable but significantly lower performance. | P118: Peak performance was in 2012, followed by a gradual decline.
P119: Asia remains stable but significantly lower in profit.
P120: Asia remains stable but significantly lower in profit.
A160: No consistent seasonality observed. Profit fluctuates across months, with occasional spikes driven by specific countries. | K160: No consistent growth trend observed. Profit varies across years, with Poland showing the highest volatility.

Sheet 10.Profit by weekday

Sheet 11.Dashboard
I2: Total number of orders | J2: =COUNTA(events!A2:A1000) -> 1330
I3: Total profit | J3: =SUM(events!W2:W1000) -> 501434459
I4: Total number of contries | J4: =IFERROR(__xludf.DUMMYFUNCTION("COUNTUNIQUE(events!J2:J1000)"),46.0) -> 46
I5: Total revenue | J5: =SUM(events!U2:U1000) -> 1702129408
C8: Profit by Countries

Sheet 12.ABC Analysis
G1: ABC Analysis by Category
G2: Category | H2: Total profit | I2: % of total | J2: Cumulative % | K2: ABC
G3: Cosmetics | H3: 10833318 | I3: =H3 / SUM($H$3:$H$13) -> 0.27848864 | J3: =SUM($I$3:I3) -> 0.27848864 | K3: =IF(J3<=0.8,"A",IF(J3<=0.95,"B","C")) -> A
G4: Office Supplies | H4: 6632543.8 | I4: =H4 / SUM($H$3:$H$13) -> 0.17050068 | J4: =SUM($I$3:I4) -> 0.44898932 | K4: =IF(J4<=0.8,"A",IF(J4<=0.95,"B","C")) -> A
G5: Household | H5: 5500910.2 | I5: =H5 / SUM($H$3:$H$13) -> 0.14141014 | J5: =SUM($I$3:I5) -> 0.59039946 | K5: =IF(J5<=0.8,"A",IF(J5<=0.95,"B","C")) -> A
G6: Baby Food | H6: 4088851.6 | I6: =H6 / SUM($H$3:$H$13) -> 0.1051108 | J6: =SUM($I$3:I6) -> 0.69551026 | K6: =IF(J6<=0.8,"A",IF(J6<=0.95,"B","C")) -> A
G7: Clothes | H7: 2953663.3 | I7: =H7 / SUM($H$3:$H$13) -> 0.075928878 | J7: =SUM($I$3:I7) -> 0.77143914 | K7: =IF(J7<=0.8,"A",IF(J7<=0.95,"B","C")) -> A
G8: Cereal | H8: 2500898.4 | I8: =H8 / SUM($H$3:$H$13) -> 0.064289795 | J8: =SUM($I$3:I8) -> 0.83572893 | K8: =IF(J8<=0.8,"A",IF(J8<=0.95,"B","C")) -> B
G9: Vegetables | H9: 2204971.7 | I9: =H9 / SUM($H$3:$H$13) -> 0.056682503 | J9: =SUM($I$3:I9) -> 0.89241143 | K9: =IF(J9<=0.8,"A",IF(J9<=0.95,"B","C")) -> B
G10: Meat | H10: 1777615.2 | I10: =H10 / SUM($H$3:$H$13) -> 0.045696585 | J10: =SUM($I$3:I10) -> 0.93810802 | K10: =IF(J10<=0.8,"A",IF(J10<=0.95,"B","C")) -> B
G11: Snacks | H11: 1267739.6 | I11: =H11 / SUM($H$3:$H$13) -> 0.032589377 | J11: =SUM($I$3:I11) -> 0.9706974 | K11: =IF(J11<=0.8,"A",IF(J11<=0.95,"B","C")) -> C
G12: Personal Care | H12: 648828.46 | I12: =H12 / SUM($H$3:$H$13) -> 0.016679226 | J12: =SUM($I$3:I12) -> 0.98737662 | K12: =IF(J12<=0.8,"A",IF(J12<=0.95,"B","C")) -> C
G13: Beverages | H13: 491054.37 | I13: =H13 / SUM($H$3:$H$13) -> 0.012623378 | J13: =SUM($I$3:I13) -> 1 | K13: =IF(J13<=0.8,"A",IF(J13<=0.95,"B","C")) -> C
G14: Fruits | H14: 99296.82 | I14: =H14 / SUM($H$3:$H$13) -> 0.0025525916 | J14: =SUM($I$3:I14) -> 1.0025526 | K14: =IF(J14<=0.8,"A",IF(J14<=0.95,"B","C")) -> C

Sheet 13.ABC visualization 
A1: Category | B1: Total profit | C1: % of total | D1: Cumulative % | E1: ABC | I1: Category | J1: Total revenue | K1: % of total | L1: Cumulative % | M1: ABC | Q1: Category | R1: Profit ABC | S1: Revenue ABC | T1: Profit | U1: Revenue
A2: Cosmetics | B2: 10833318 | C2: =B2/ SUM($B$2:$B$13) -> 0.27777958 | D2: =SUM($C$2:C2) -> 0.27777958 | E2: A | I2: Office Supplies | J2: 34211317 | K2: =J2 / SUM($J$2:$J$13) -> 0.25044801 | L2: =SUM($K$2:K2) -> 0.25044801 | M2: =IF(L2<=0.8,"A",IF(L2<=0.95,"B","C")) -> A | Q2: Cosmetics | R2: =VLOOKUP(A2,$A$2:$E$13,5,FALSE) -> A | S2: =VLOOKUP(A2,$I$2:$M$13,5,FALSE) -> A | T2: =VLOOKUP(Q2,$A$2:$E$13,2,FALSE) -> 10833318 | U2: =VLOOKUP(Q2,$I$2:$M$13,2,FALSE) -> 27240620
A3: Office Supplies | B3: 6632543.8 | C3: =B3/ SUM($B$2:$B$13) -> 0.17006657 | D3: =SUM($C$2:C3) -> 0.44784615 | E3: A | I3: Cosmetics | J3: 27240620 | K3: =J3 / SUM($J$2:$J$13) -> 0.1994182 | L3: =SUM($K$2:K3) -> 0.44986621 | M3: =IF(L3<=0.8,"A",IF(L3<=0.95,"B","C")) -> A | Q3: Office Supplies | R3: =VLOOKUP(A3,$A$2:$E$13,5,FALSE) -> A | S3: =VLOOKUP(A3,$I$2:$M$13,5,FALSE) -> A | T3: =VLOOKUP(Q3,$A$2:$E$13,2,FALSE) -> 6632543.8 | U3: =VLOOKUP(Q3,$I$2:$M$13,2,FALSE) -> 34211317
A4: Household | B4: 5500910.2 | C4: =B4/ SUM($B$2:$B$13) -> 0.14105009 | D4: =SUM($C$2:C4) -> 0.58889625 | E4: A | I4: Household | J4: 22181218 | K4: =J4 / SUM($J$2:$J$13) -> 0.16238024 | L4: =SUM($K$2:K4) -> 0.61224645 | M4: =IF(L4<=0.8,"A",IF(L4<=0.95,"B","C")) -> A | Q4: Household | R4: =VLOOKUP(A4,$A$2:$E$13,5,FALSE) -> A | S4: =VLOOKUP(A4,$I$2:$M$13,5,FALSE) -> A | T4: =VLOOKUP(Q4,$A$2:$E$13,2,FALSE) -> 5500910.2 | U4: =VLOOKUP(Q4,$I$2:$M$13,2,FALSE) -> 22181218
A5: Baby Food | B5: 4088851.6 | C5: =B5/ SUM($B$2:$B$13) -> 0.10484318 | D5: =SUM($C$2:C5) -> 0.69373943 | E5: A | I5: Cereal | J5: 18445875 | K5: =J5 / SUM($J$2:$J$13) -> 0.13503522 | L5: =SUM($K$2:K5) -> 0.74728167 | M5: =IF(L5<=0.8,"A",IF(L5<=0.95,"B","C")) -> A | Q5: Baby Food | R5: =VLOOKUP(A5,$A$2:$E$13,5,FALSE) -> A | S5: =VLOOKUP(A5,$I$2:$M$13,5,FALSE) -> B | T5: =VLOOKUP(Q5,$A$2:$E$13,2,FALSE) -> 4088851.6 | U5: =VLOOKUP(Q5,$I$2:$M$13,2,FALSE) -> 11314417
A6: Clothes | B6: 2953663.3 | C6: =B6/ SUM($B$2:$B$13) -> 0.075735556 | D6: =SUM($C$2:C6) -> 0.76947498 | E6: A | I6: Baby Food | J6: 11314417 | K6: =J6 / SUM($J$2:$J$13) -> 0.082828536 | L6: =SUM($K$2:K6) -> 0.8301102 | M6: =IF(L6<=0.8,"A",IF(L6<=0.95,"B","C")) -> B | Q6: Clothes | R6: =VLOOKUP(A6,$A$2:$E$13,5,FALSE) -> A | S6: =VLOOKUP(A6,$I$2:$M$13,5,FALSE) -> B | T6: =VLOOKUP(Q6,$A$2:$E$13,2,FALSE) -> 2953663.3 | U6: =VLOOKUP(Q6,$I$2:$M$13,2,FALSE) -> 7208005.2
A7: Cereal | B7: 2500898.4 | C7: =B7/ SUM($B$2:$B$13) -> 0.064126107 | D7: =SUM($C$2:C7) -> 0.83360109 | E7: B | I7: Clothes | J7: 7208005.2 | K7: =J7 / SUM($J$2:$J$13) -> 0.052767059 | L7: =SUM($K$2:K7) -> 0.88287726 | M7: =IF(L7<=0.8,"A",IF(L7<=0.95,"B","C")) -> B | Q7: Cereal | R7: =VLOOKUP(A7,$A$2:$E$13,5,FALSE) -> B | S7: =VLOOKUP(A7,$I$2:$M$13,5,FALSE) -> A | T7: =VLOOKUP(Q7,$A$2:$E$13,2,FALSE) -> 2500898.4 | U7: =VLOOKUP(Q7,$I$2:$M$13,2,FALSE) -> 18445875
A8: Vegetables | B8: 2204971.7 | C8: =B8/ SUM($B$2:$B$13) -> 0.056538184 | D8: =SUM($C$2:C8) -> 0.89013927 | E8: B | I8: Vegetables | J8: 5871950.6 | K8: =J8 / SUM($J$2:$J$13) -> 0.042986312 | L8: =SUM($K$2:K8) -> 0.92586357 | M8: =IF(L8<=0.8,"A",IF(L8<=0.95,"B","C")) -> B | Q8: Vegetables | R8: =VLOOKUP(A8,$A$2:$E$13,5,FALSE) -> B | S8: =VLOOKUP(A8,$I$2:$M$13,5,FALSE) -> B | T8: =VLOOKUP(Q8,$A$2:$E$13,2,FALSE) -> 2204971.7 | U8: =VLOOKUP(Q8,$I$2:$M$13,2,FALSE) -> 5871950.6
A9: Meat | B9: 1777615.2 | C9: =B9/ SUM($B$2:$B$13) -> 0.045580238 | D9: =SUM($C$2:C9) -> 0.93571951 | E9: B | I9: Snacks | J9: 3841267.3 | K9: =J9 / SUM($J$2:$J$13) -> 0.028120454 | L9: =SUM($K$2:K9) -> 0.95398403 | M9: =IF(L9<=0.8,"A",IF(L9<=0.95,"B","C")) -> C | Q9: Meat | R9: =VLOOKUP(A9,$A$2:$E$13,5,FALSE) -> B | S9: =VLOOKUP(A9,$I$2:$M$13,5,FALSE) -> C | T9: =VLOOKUP(Q9,$A$2:$E$13,2,FALSE) -> 1777615.2 | U9: =VLOOKUP(Q9,$I$2:$M$13,2,FALSE) -> 2645122.4
A10: Snacks | B10: 1267739.6 | C10: =B10/ SUM($B$2:$B$13) -> 0.032506402 | D10: =SUM($C$2:C10) -> 0.96822591 | E10: C | I10: Meat | J10: 2645122.4 | K10: =J10 / SUM($J$2:$J$13) -> 0.019363933 | L10: =SUM($K$2:K10) -> 0.97334796 | M10: =IF(L10<=0.8,"A",IF(L10<=0.95,"B","C")) -> C | Q10: Snacks | R10: =VLOOKUP(A10,$A$2:$E$13,5,FALSE) -> C | S10: =VLOOKUP(A10,$I$2:$M$13,5,FALSE) -> C | T10: =VLOOKUP(Q10,$A$2:$E$13,2,FALSE) -> 1267739.6 | U10: =VLOOKUP(Q10,$I$2:$M$13,2,FALSE) -> 3841267.3
A11: Personal Care | B11: 648828.46 | C11: =B11/ SUM($B$2:$B$13) -> 0.016636759 | D11: =SUM($C$2:C11) -> 0.98486267 | E11: C | I11: Personal Care | J11: 2116071.4 | K11: =J11 / SUM($J$2:$J$13) -> 0.015490952 | L11: =SUM($K$2:K11) -> 0.98883891 | M11: =IF(L11<=0.8,"A",IF(L11<=0.95,"B","C")) -> C | Q11: Personal Care | R11: =VLOOKUP(A11,$A$2:$E$13,5,FALSE) -> C | S11: =VLOOKUP(A11,$I$2:$M$13,5,FALSE) -> C | T11: =VLOOKUP(Q11,$A$2:$E$13,2,FALSE) -> 648828.46 | U11: =VLOOKUP(Q11,$I$2:$M$13,2,FALSE) -> 2116071.4
A12: Beverages | B12: 491054.37 | C12: =B12/ SUM($B$2:$B$13) -> 0.012591237 | D12: =SUM($C$2:C12) -> 0.99745391 | E12: C | I12: Beverages | J12: 1140195.1 | K12: =J12 / SUM($J$2:$J$13) -> 0.0083469337 | L12: =SUM($K$2:K12) -> 0.99718585 | M12: =IF(L12<=0.8,"A",IF(L12<=0.95,"B","C")) -> C | Q12: Beverages | R12: =VLOOKUP(A12,$A$2:$E$13,5,FALSE) -> C | S12: =VLOOKUP(A12,$I$2:$M$13,5,FALSE) -> C | T12: =VLOOKUP(Q12,$A$2:$E$13,2,FALSE) -> 491054.37 | U12: =VLOOKUP(Q12,$I$2:$M$13,2,FALSE) -> 1140195.1
A13: Fruits | B13: 99296.82 | C13: =B13/ SUM($B$2:$B$13) -> 0.0025460924 | D13: =SUM($C$2:C13) -> 1 | E13: C | I13: Fruits | J13: 384414.66 | K13: =J13 / SUM($J$2:$J$13) -> 0.0028141532 | L13: =SUM($K$2:K13) -> 1 | M13: =IF(L13<=0.8,"A",IF(L13<=0.95,"B","C")) -> C | Q13: Fruits | R13: =VLOOKUP(A13,$A$2:$E$13,5,FALSE) -> C | S13: =VLOOKUP(A13,$I$2:$M$13,5,FALSE) -> C | T13: =VLOOKUP(Q13,$A$2:$E$13,2,FALSE) -> 99296.82 | U13: =VLOOKUP(Q13,$I$2:$M$13,2,FALSE) -> 384414.66
A15: Total | B15: =SUM(B2:B13) -> 38999691 | C15: =SUM(C2:C13) -> 1 | I15: Total | J15: =SUM(J2:J13) -> 1.3660047e+08 | K15: =SUM(K2:K13) -> 1
W19: Key Insights:
W20: • A categories generate the majority of revenue and profit
W21: • Cereal has high revenue but lower profit, indicating lower margins
W22: • Cereal has high revenue but lower profit, indicating lower margins
W23: • C categories contribute minimally and may require optimization
A41: Category | B41: Total cost | C41: % of total | D41: Cumulative % | E41: ABC
A42: Office Supplies | B42: 27578774 | C42: =B42/SUM($B$42:$B$53) -> 0.28256714 | D42: =SUM($C$42:C42) -> 0.28256714 | E42: =IF(D2<=0.8,"A",IF(D2<=0.95,"B","C")) -> A
A43: Household | B43: 16680308 | C43: =B43/SUM($B$42:$B$53) -> 0.17090342 | D43: =SUM($C$42:C43) -> 0.45347056 | E43: =IF(D3<=0.8,"A",IF(D3<=0.95,"B","C")) -> A
A44: Cosmetics | B44: 16407302 | C44: =B44/SUM($B$42:$B$53) -> 0.16810626 | D44: =SUM($C$42:C44) -> 0.62157681 | E44: =IF(D4<=0.8,"A",IF(D4<=0.95,"B","C")) -> A
A45: Meat | B45: 15944976 | C45: =B45/SUM($B$42:$B$53) -> 0.16336935 | D45: =SUM($C$42:C45) -> 0.78494616 | E45: =IF(D5<=0.8,"A",IF(D5<=0.95,"B","C")) -> A
A46: Snacks | B46: 7225565.8 | C46: =B46/SUM($B$42:$B$53) -> 0.074031842 | D46: =SUM($C$42:C46) -> 0.858978 | E46: =IF(D6<=0.8,"A",IF(D6<=0.95,"B","C")) -> A
A47: Vegetables | B47: 4254341.9 | C47: =B47/SUM($B$42:$B$53) -> 0.043589219 | D47: =SUM($C$42:C47) -> 0.90256722 | E47: =IF(D7<=0.8,"A",IF(D7<=0.95,"B","C")) -> B
A48: Baby Food | B48: 3666978.8 | C48: =B48/SUM($B$42:$B$53) -> 0.037571203 | D48: =SUM($C$42:C48) -> 0.94013843 | E48: =IF(D8<=0.8,"A",IF(D8<=0.95,"B","C")) -> B
A49: Beverages | B49: 2573527.7 | C49: =B49/SUM($B$42:$B$53) -> 0.0263679 | D49: =SUM($C$42:C49) -> 0.96650633 | E49: =IF(D9<=0.8,"A",IF(D9<=0.95,"B","C")) -> B
A50: Personal Care | B50: 1467243 | C50: =B50/SUM($B$42:$B$53) -> 0.015033107 | D50: =SUM($C$42:C50) -> 0.98153943 | E50: =IF(D10<=0.8,"A",IF(D10<=0.95,"B","C")) -> C
A51: Clothes | B51: 867507.2 | C51: =B51/SUM($B$42:$B$53) -> 0.0088883222 | D51: =SUM($C$42:C51) -> 0.99042776 | E51: =IF(D11<=0.8,"A",IF(D11<=0.95,"B","C")) -> C
A52: Cereal | B52: 649140.73 | C52: =B52/SUM($B$42:$B$53) -> 0.0066509787 | D52: =SUM($C$42:C52) -> 0.99707873 | E52: =IF(D12<=0.8,"A",IF(D12<=0.95,"B","C")) -> C
A53: Fruits | B53: 285117.84 | C53: =B53/SUM($B$42:$B$53) -> 0.0029212659 | D53: =SUM($C$42:C53) -> 1 | E53: =IF(D13<=0.8,"A",IF(D13<=0.95,"B","C")) -> C
A55: Total | B55: =SUM(B42:B53) -> 97600783 | C55: =SUM(C42:C53) -> 1
